Workbook

Sheet Allocation of Jan-26 
B1: Cost of placement | C1: FV of placement | D1: Closing Balance as at Dec'25 | E1: Closing Balance - (31-Jan-2026) | F1: Concentration (%) - (31-Jan-2026) | G1: Revised Placement | H1: Concentration (%) | I1: Holding Period | J1: Days to Maturity | K1: Weighted Maturity | L1: Placement % | M1: Weighted Placements
A2: MTBs (1Y) | B2: 1999988012 | C2: 2.0572194e+09 | D2: =C2 -> 2057219450 | E2: 2.1114701e+09 | F2: =C2/$E$13 -> 0.21955012 | G2: =D2 -> 2057219450 | H2: =E2/$E$13 -> 0.22533985 | I2: 31 | J2: =218-I2 -> 187 | K2: =C2/SUM($E$2:$E$12)*J2 -> 41.055873 | L2: =I2/31 -> 1 | M2: =E2*L2 -> 2111470084
A3: MTBs (3M) | B3: 487745500 | C3: =B3 -> 487745500 | D3: =C3 -> 487745500 | E3: 4.9255976e+08 | F3: =C3/$E$13 -> 0.052053069 | G3: =E3 -> 4.9255976e+08 | H3: =E3/$E$13 -> 0.052566855 | I3: 31 | J3: =64-I3 -> 33 | K3: =C3/SUM($E$2:$E$12)*J3 -> 1.7177513 | L3: =I3/31 -> 1 | M3: =E3*L3 -> 4.9255976e+08
A4: MTBs (6M) | B4: 474182500 | C4: =B4 -> 474182500 | D4: =C4 -> 474182500 | E4: 4.9276545e+08 | F4: =C4/$E$13 -> 0.050605601 | G4: =E4 -> 492765455 | H4: =E4/$E$13 -> 0.052588807 | I4: 31 | J4: =162-I4 -> 131 | K4: =C4/SUM($E$2:$E$12)*J4 -> 6.6293338 | L4: =I4/31 -> 1 | M4: =E4*L4 -> 492765455
A5: Faysal Bank | B5: 1601144278 | C5: 1055368872 | D5: =C5 -> 1055368872 | E5: 3020864339 | F5: =C5/$E$13 -> 0.11263085 | G5: 2000000000 | H5: =E5/$E$13 -> 0.32239202 | I5: 31 | J5: 0 | K5: =C5/SUM($E$2:$E$12)*J5 -> 0 | L5: =I5/31 -> 1 | M5: =E5*L5 -> 3020864339
A6: Samba Bank | B6: 1329131526 | C6: 1028157070 | D6: =C6 -> 1028157070 | E6: 556124.26 | F6: =C6/$E$13 -> 0.10972675 | G6: =E6 -> 556124.26 | H6: =E6/$E$13 -> 5.9350572e-05 | I6: 31 | J6: 0 | K6: =C6/SUM($E$2:$E$12)*J6 -> 0 | L6: =I6/31 -> 1 | M6: =E6*L6 -> 556124.26
A7: TDR | B7: 1000000000 | C7: 1000000000 | D7: =C7 -> 1000000000 | E7: 0 | F7: =C7/$E$13 -> 0.10672178 | G7: =E7 -> 0 | H7: =E7/$E$13 -> 0 | I7: 31 | J7: 0 | K7: =C7/SUM($E$2:$E$12)*J7 -> 0 | L7: =I7/31 -> 1 | M7: =E7*L7 -> 0
A8: COI | B8: 1300000000 | C8: 1300000000 | D8: =C8 -> 1300000000 | E8: =D8 -> 1300000000 | F8: =C8/$E$13 -> 0.13873832 | G8: =E8 -> 1300000000 | H8: =E8/$E$13 -> 0.13873832 | I8: 31 | J8: 30 | K8: =C8/SUM($E$2:$E$12)*J8 -> 4.1621495 | L8: =I8/31 -> 1 | M8: =E8*L8 -> 1300000000
A9: Alfalah Government Securities Fund Plan II | B9: 816606719 | C9: 827108187 | D9: =C9 -> 827108187 | E9: 833081692 | F9: =C9/$E$13 -> 0.088270459 | G9: =E9 -> 833081692 | H9: =E9/$E$13 -> 0.088907962 | I9: 31 | J9: 271 | K9: =C9/SUM($E$2:$E$12)*J9 -> 23.921294 | L9: =I9/31 -> 1 | M9: =E9*L9 -> 833081692
A10: Alfalah MTS Fund (Formerly: Faysal MTS Fund) | B10: 303753987 | C10: 306538002 | D10: =C10 -> 306538002 | E10: 309361746 | F10: =C10/$E$13 -> 0.032714282 | G10: =E10 -> 309361746 | H10: =E10/$E$13 -> 0.033015637 | I10: 31 | J10: 0 | K10: =C10/SUM($E$2:$E$12)*J10 -> 0 | L10: =I10/31 -> 1 | M10: =E10*L10 -> 309361746
A11: Alfalah Income Multiplier | E11: 0 | F11: =C11/$E$13 -> 0 | G11: =D23*0.3 -> 300000000 | H11: =E11/$E$13 -> 0 | I11: 31 | J11: 0 | K11: =C11/SUM($E$2:$E$12)*J11 -> 0 | L11: =I11/31 -> 1 | M11: =E11*L11 -> 0
A12: MCB Investment Saving Plan I | B12: 800000000 | C12: 802654992 | D12: =C12 -> 802654992 | E12: 8.0949922e+08 | F12: =C12/$E$13 -> 0.085660771 | G12: =E12 -> 8.0949922e+08 | H12: =E12/$E$13 -> 0.086391199 | I12: 31 | J12: 1 | K12: =C12/SUM($E$2:$E$12)*J12 -> 0.085660771 | L12: =I12/31 -> 1 | M12: =E12*L12 -> 8.0949922e+08
A13: Total Income | C13: =SUM(C2:C12) -> 9338974573 | D13: =SUM(D2:D12) -> 9338974573 | E13: =SUM(E2:E12) -> 9370158424 | F13: =SUM(F2:F12) -> 0.996672 | G13: =SUM(G2:G12) -> 8595043451 | H13: =SUM(H2:H12) -> 1 | K13: =SUM(K2:K12) -> 77.572063 | M13: =SUM(M2:M12) -> 9370158424
B16: Finance Cost
B17: =10.63%-C17 -> 0.1058 | C17: 0.0005 | K17: 1300 | L17: 0.1005 | M17: =L17*K17 -> 130.65
K18: 1238 | L18: 0.1075 | M18: =L18*K18 -> 133.085
C19: Funds Available | D19: =D5+D6+D7 -> 3083525942 | I19: bench | K19: 1238 | L19: =B17 -> 0.1058 | M19: =L19*K19 -> 130.9804
C20: Funds in Samba for operations | D20: =D19-D21 -> 83525942 | E20: (will be moved to Faysal in this week) | L20: =L18-L19 -> 0.0017 | M20: =M17+M18-M19 -> 132.7546
B21: Currently | C21: Placement in Faysal | D21: 3000000000 | M21: =M20/K17 -> 0.10211892
C22: Faysal Saving Account @ 10.25% | D22: 2000000000 | M22: =M21-10.38% -> -0.0016810769
C23: Allocation Available | D23: =D21-D22 -> 1000000000
D25: % to Total Portfolio
A26: Exposure in Alfalah | B26: Current | C26: =G9+G10 -> 1142443438 | D26: =C26/G13 -> 0.13291887 | I26: 2019-20 (12m) | J26: 2020-21 (12m) | K26: 2021-22 (12m) | L26: 2022-23 (12m) | M26: 2023-24 (12m) | N26: 2024-25 (12m) | O26: July-Nov 2025 (5m)
B27: Additional Investment | C27: =C26+G11 -> 1442443438 | D27: =C27/G13 -> 0.1678227 | I27: 13066 | J27: 16694 | K27: 24891 | L27: 52779 | M27: 37386 | N27: 48905 | O27: 5167
I28: 83 | J28: 104 | K28: 140 | L28: 213 | M28: 132 | N28: 175 | O28: 18
I29: 158 | J29: 160 | K29: 177 | L29: 248 | M29: 283 | N29: 279 | O29: 282

Sheet Allocation Strategy
B2: Current | I2: Allocation Available
B3: Allocation Available (PKR'Mn) | D3: =J8 -> 3000 | I3: TDR | J3: 1000
B4: Month | D4: 1 | I4: Faysal - Saving | J4: 1058
I5: Samba - Saving | J5: 1022
B6: Particular | C6: % of Allocation | D6: Rate | E6: Amount (PKR'Mn) | G6: Reason | I6: Available Allocation | J6: =SUM(J3:J5) -> 3080
B7: Faysal Saving | C7: =E7/$D$3 -> 1 | D7: 0.1025 | E7: =J8 -> 3000 | F7: =E7*(D7*1/12) -> 25.625 | G7: Keep the funds till MPC | I7: Operating Cost | J7: -80
B8: Income Multiplier | C8: =E8/$D$3 -> 0 | D8: 0.107 | E8: 0 | F8: =E8*(D8*1/12) -> 0 | G8: Investment in Mutual Fund | J8: =J6+J7 -> 3000
B9: Sovereign Fund / GSF | C9: =E9/$D$3 -> 0 | D9: 0.105 | E9: 0 | F9: =E9*(D9*1/12) -> 0 | G9: Investment in Mutual Fund
B10: 12 MTB | C10: =E10/$D$3 -> 0 | D10: 0.1014 | E10: 0 | F10: =E10*(D10*1/12) -> 0 | G10: Placement in 3MTBs directly | J10: Rates | K10: Amount | L10: Annualized | M10: Monthly
B11: 3 MTBs | C11: =E11/$D$3 -> 0 | D11: 0.1005 | E11: 0 | F11: =E11*(D11*1/12) -> 0 | I11: Finance Cost | J11: 0.1058 | K11: -1238 | L11: =(K11*J11) -> -130.9804 | M11: =K11*J11*1/12 -> -10.915033
B12: MCB Pakistan Sovereign Fund | C12: =E12/$D$3 -> 0 | D12: 0.1025 | I12: COI (Placement) | J12: 0.1005 | K12: 1300 | L12: =(K12*J12) -> 130.65 | M12: =K12*J12*1/12 -> 10.8875
B13: Total | C13: =SUM(C7:C10) -> 1 | E13: =SUM(E7:E11) -> 3000 | F13: =SUM(F7:F11)+F186 -> 25.625 | J13: =J12-J11 -> -0.0053 | L13: =L11+L12 -> -0.3304 | M13: =M11+M12 -> -0.027533333
B14: Avg return | F14: =(F13/E13)*12/1 -> 0.1025
I15: Currently Placement
B16: Recommendation - 1 | C16: Allocation Available | E16: 1000 | I16: Faysal Saving Account | J16: =F14 -> 0.1025 | K16: =E13 -> 3000 | L16: =K16*J16 -> 307.5 | M16: =L16*1/12 -> 25.625
B17: Faysal Saving Account | C17: =E17/E23 -> 0.9 | D17: 0.1025 | E17: =(D3-E18) -> 2700 | F17: =E17*(D17*1/12) -> 23.0625 | G17: Keep the funds till MPC | I17: Total Placement (Including COIs) | K17: =K16+K12 -> 4300
B18: Income Multiplier | C18: =E18/$D$3 -> 0.1 | D18: 0.107 | E18: =E16*0.3 -> 300 | F18: =E18*(D18*1/12) -> 2.675 | G18: Diversify investment in MF for Yield of 50bps | I18: Total Income (Including COIs) | L18: =L16+L12 -> 438.15 | M18: =M16+M12 -> 36.5125
B19: Sovereign Fund / GSF | C19: =E19/$D$3 -> 0 | D19: 0.105 | E19: 0 | F19: =E19*(D19*1/12) -> 0 | I19: Expense | L19: =L11 -> -130.9804 | M19: =M11 -> -10.915033
B20: 12 MTB | C20: =E20/$D$3 -> 0 | D20: 0.1014 | E20: 0 | F20: =E20*(D20*1/12) -> 0 | I20: Net Carry (Amount) | L20: =L18+L19 -> 307.1696 | M20: =M18+M19 -> 25.597467
B21: AKD Aggressive Income Fund | C21: =E21/$D$3 -> 0 | D21: 0.1005 | E21: 0 | F21: =E21*(D21*1/12) -> 0 | G21: Diversify investment in MF for Yield of 50bps | I21: Net Carry (%) | L21: =L20/K17 -> 0.071434791 | M21: =(M20/K17)*12/1 -> 0.071434791
B22: 3 MTBs | C22: =E22/$D$3 -> 0 | D22: 0.1025 | E22: 0 | F22: =E22*(D22*1/12) -> 0
B23: Total | C23: =SUM(C17:C20) -> 1 | E23: =SUM(E17:E22) -> 3000 | F23: =SUM(F17:F21)+F195 -> 25.7375 | I23: Recommendation - 1
B24: Avg return | F24: =(F23/E23)*12/1 -> 0.10295 | I24: Faysal Saving | J24: =J16 -> 0.1025 | K24: =E17 -> 2700 | L24: =K24*J24 -> 276.75 | M24: =L24*1/12 -> 23.0625
I25: =B18 -> Income Multiplier | J25: =D18 -> 0.107 | K25: =E18 -> 300 | L25: =K25*J25 -> 32.1 | M25: =L25*1/12 -> 2.675
B26: Recommendation - 2 | C26: Allocation Available | E26: 1000 | I26: Total Placement (Including COIs) | K26: =K24+K25+K12 -> 4300
B27: Faysal Saving Account | C27: =E27/E33 -> 0.66666667 | D27: 0.1025 | E27: =D3-E26 -> 2000 | F27: =E27*(D27*1/12) -> 17.083333 | G27: Keep the funds till MPC | I27: Total Income (Including COIs) | L27: =L24+L25+L12 -> 439.5 | M27: =L27*1/12 -> 36.625
B28: Income Multiplier | C28: =E28/$D$3 -> 0.1 | D28: 0.107 | E28: =E26*0.3 -> 300 | F28: =E28*(D28*1/12) -> 2.675 | G28: Diversify investment in MF for Yield of 50bps | I28: Expense | L28: =L11 -> -130.9804 | M28: =L28*1/12 -> -10.915033
B29: Sovereign Fund / GSF | C29: =E29/$D$3 -> 0 | D29: 0.105 | E29: 0 | F29: =E29*(D29*1/12) -> 0 | I29: Net Carry (Amount) | L29: =L27+L28 -> 308.5196 | M29: =L29*1/12 -> 25.709967
B30: 12 MTB | C30: =E30/$D$3 -> 0 | D30: 0.1014 | E30: 0 | F30: =E30*(D30*1/12) -> 0 | I30: Net Carry (%) | L30: =L29/K26 -> 0.071748744 | M30: =M29/K26*12/1 -> 0.071748744
B31: AKD Aggressive Income Fund | C31: =E31/$D$3 -> 0.23333333 | D31: 0.107 | E31: 700 | F31: =E31*(D31*1/12) -> 6.2416667 | G31: Diversify investment in MF for Yield of 50bps
B32: 3 MTBs | D32: 0.1025 | I32: Recommendation - 2
B33: Total | C33: =SUM(C27:C30) -> 0.76666667 | E33: =SUM(E27:E31) -> 3000 | F33: =SUM(F27:F31)+F206 -> 26 | I33: Faysal Saving | J33: =D27 -> 0.1025 | K33: =E27 -> 2000 | L33: =K33*J33 -> 205 | M33: =L33*1/12 -> 17.083333
B34: Avg return | F34: =(F33/E33)*12/1 -> 0.104 | I34: =B28 -> Income Multiplier | J34: =D28 -> 0.107 | K34: =E28 -> 300 | L34: =K34*J34 -> 32.1 | M34: =L34*1/12 -> 2.675
B35: *Diversified the Fund due to a total exposure on Alfalah will increase to 15% of portfolio | I35: =B31 -> AKD Aggressive Income Fund | J35: =D29 -> 0.105 | K35: =E31 -> 700 | L35: =K35*J35 -> 73.5 | M35: =L35*1/12 -> 6.125
I36: =I26 -> Total Placement (Including COIs) | K36: =K33+K34+K35+K12 -> 4300 | L36: =L35+L34+L33+L12 -> 441.25 | M36: =L36*1/12 -> 36.770833
B37: Recommendation - 3 | C37: Allocation Available | E37: 1000
B38: Faysal Saving Account | C38: =E38/E45 -> 0.65217391 | D38: 0.1025 | E38: =E13-E37-E44 -> 1500 | F38: =E38*(D38*1/12) -> 12.8125 | G38: Keep the funds till MPC | I38: Total Income (Including COIs) | L38: =L36 -> 441.25 | M38: =L38*1/12 -> 36.770833
B39: Income Multiplier | C39: =E39/$D$3 -> 0.1 | D39: 0.107 | E39: =E37*0.3 -> 300 | F39: =E39*(D39*1/12) -> 2.675 | G39: Diversify investment in MF for Yield of 50bps | I39: Expense | L39: =L11 -> -130.9804 | M39: =L39*1/12 -> -10.915033
B40: Sovereign Fund / GSF | C40: =E40/$D$3 -> 0 | D40: 0.105 | E40: 0 | F40: =E40*(D40*1/12) -> 0 | I40: Net Carry (Amount) | L40: =L38+L39 -> 310.2696 | M40: =L40*1/12 -> 25.8558
B41: 12 MTB | C41: =E41/$D$3 -> 0 | D41: 0.1014 | E41: 0 | F41: =E41*(D41*1/12) -> 0 | I41: Net Carry (%) | L41: =L40/K36 -> 0.072155721 | M41: =M40/K36*12/1 -> 0.072155721
B42: AKD Aggressive Income Fund | C42: =E42/$D$3 -> 0 | D42: 0.107 | E42: 0 | F42: =E42*(D42*1/12) -> 0 | G42: Diversify investment in MF for Yield of 50bps
B43: 3 MTBs | C43: =E43/$D$3 -> 0 | D43: 0.1025 | E43: 0 | F43: =E43*(D43*1/12) -> 0
B44: 3Year PIB | C44: =E44/$D$3 -> 0.16666667 | D44: 0.1024 | E44: 500 | F44: =E44*D44*3/36 -> 4.2666667 | G44: =30*12*3 -> 1080 | I44: Impact of Interest Rate Change
B45: Total | C45: =SUM(C38:C41) -> 0.75217391 | E45: =SUM(E38:E44) -> 2300 | F45: =SUM(F38:F44)+F218 -> 19.754167 | G45: =12*3 -> 36 | I45: No Change | J45: 25 | K45: 50 | L45: 75
B46: Avg return | F46: =(F45/E45)*12/1 -> 0.10306522 | I46: 0.1025 | J46: 0.1 | K46: 0.0975 | L46: 0.095
B47: *Diversified the Fund due to a total exposure on Alfalah will increase to 15% of portfolio | H47: PIBs | I47: =$I$54/J54 -> 4761904762
H48: Income Multiplier
H49: Savings
H52: Current Allocation | I52: 1000000000 | J52: in Bank Placement at 10.25%
H53: In case of rate cut
H54: PIBs | I54: 500000000 | J54: 0.105
H55: Income Multiplier | I55: 300000000 | J55: 0.107
H56: Savings | I56: 200000000 | J56: 0.1025

Sheet Jan-26 
B1: Cost of placement | C1: FV of placement | D1: Closing Balance as at Dec'25 | E1: New Placements - (12-Jan-2026) | F1: Concentration (%) - (12-Jan-2026) | G1: Revised Placement | H1: Concentration (%) | I1: Holding Period | J1: Days to Maturity | K1: Weighted Maturity | L1: Placement % | M1: Weighted Placements
A2: MTBs (1Y) | B2: 1999988012 | C2: 2.0572194e+09 | D2: =C2 -> 2057219450 | E2: =D2 -> 2057219450 | F2: =C2/$E$14 -> 0.22028323 | G2: =D2 -> 2057219450 | H2: =E2/$E$14 -> 0.22028323 | I2: 31 | J2: 187 | K2: =C2/SUM($E$2:$E$13)*J2 -> 41.192963 | L2: =I2/31 -> 1 | M2: =E2*L2 -> 2057219450
A3: MTBs (3M) | B3: 487745500 | C3: =B3 -> 487745500 | D3: =C3 -> 487745500 | E3: =D3 -> 487745500 | F3: =C3/$E$14 -> 0.05222688 | G3: =E3 -> 487745500 | H3: =E3/$E$14 -> 0.05222688 | I3: 31 | J3: 33 | K3: =C3/SUM($E$2:$E$13)*J3 -> 1.723487 | L3: =I3/31 -> 1 | M3: =E3*L3 -> 487745500
A4: MTBs (6M) | B4: 474182500 | C4: =B4 -> 474182500 | D4: =C4 -> 474182500 | E4: =D4 -> 474182500 | F4: =C4/$E$14 -> 0.050774579 | G4: =E4 -> 474182500 | H4: =E4/$E$14 -> 0.050774579 | I4: 31 | J4: 131 | K4: =C4/SUM($E$2:$E$13)*J4 -> 6.6514698 | L4: =I4/31 -> 1 | M4: =E4*L4 -> 474182500
A5: Faysal Bank | B5: 1601144278 | C5: 1055368872 | D5: =C5 -> 1055368872 | E5: =(D5+D6+D7)-E6 -> 3000000000 | F5: =C5/$E$14 -> 0.11300693 | G5: 2000000000 | H5: =E5/$E$14 -> 0.32123441 | I5: 31 | J5: 0 | K5: =C5/SUM($E$2:$E$13)*J5 -> 0 | L5: =I5/31 -> 1 | M5: =E5*L5 -> 3000000000
A6: Samba Bank | B6: 1329131526 | C6: 1028157070 | D6: =C6 -> 1028157070 | E6: 83525942 | F6: =C6/$E$14 -> 0.11009314 | G6: =E6 -> 83525942 | H6: =E6/$E$14 -> 0.0089438023 | I6: 31 | J6: 0 | K6: =C6/SUM($E$2:$E$13)*J6 -> 0 | L6: =I6/31 -> 1 | M6: =E6*L6 -> 83525942
A7: TDR | B7: 1000000000 | C7: 1000000000 | D7: =C7 -> 1000000000 | E7: 0 | F7: =C7/$E$14 -> 0.10707814 | G7: =E7 -> 0 | H7: =E7/$E$14 -> 0 | I7: 31 | J7: 0 | K7: =C7/SUM($E$2:$E$13)*J7 -> 0 | L7: =I7/31 -> 1 | M7: =E7*L7 -> 0
A8: COI | B8: 1300000000 | C8: 1300000000 | D8: =C8 -> 1300000000 | E8: =D8 -> 1300000000 | F8: =C8/$E$14 -> 0.13920158 | G8: =E8 -> 1300000000 | H8: =E8/$E$14 -> 0.13920158 | I8: 31 | J8: 30 | K8: =C8/SUM($E$2:$E$13)*J8 -> 4.1760473 | L8: =I8/31 -> 1 | M8: =E8*L8 -> 1300000000
A9: Alfalah Government Securities Fund Plan II | B9: 816606719 | C9: 827108187 | D9: =C9 -> 827108187 | E9: =D9 -> 827108187 | F9: =C9/$E$14 -> 0.088565204 | G9: =E9 -> 827108187 | H9: =E9/$E$14 -> 0.088565204 | I9: 31 | J9: 0 | K9: =C9/SUM($E$2:$E$13)*J9 -> 0 | L9: =I9/31 -> 1 | M9: =E9*L9 -> 827108187
A10: Alfalah MTS Fund (Formerly: Faysal MTS Fund) | B10: 303753987 | C10: 306538002 | D10: =C10 -> 306538002 | E10: =D10 -> 306538002 | F10: =C10/$E$14 -> 0.032823518 | G10: =E10 -> 306538002 | H10: =E10/$E$14 -> 0.032823518 | I10: 31 | J10: 0 | K10: =C10/SUM($E$2:$E$13)*J10 -> 0 | L10: =I10/31 -> 1 | M10: =E10*L10 -> 306538002
A11: Alfalah Income Multiplier | B11: 500000000 | E11: 0 | F11: =C11/$E$14 -> 0 | G11: =D24*0.3 -> 300000000 | H11: =E11/$E$14 -> 0 | I11: 31 | J11: 0 | K11: =C11/SUM($E$2:$E$13)*J11 -> 0 | L11: =I11/31 -> 1 | M11: =E11*L11 -> 0
A12: MCB Investment Saving Plan I | B12: 800000000 | C12: 802654992 | D12: =C12 -> 802654992 | E12: =D12 -> 802654992 | F12: =C12/$E$14 -> 0.085946801 | G12: =E12 -> 802654992 | H12: =E12/$E$14 -> 0.085946801 | I12: 31 | J12: 0 | K12: =C12/SUM($E$2:$E$13)*J12 -> 0 | L12: =I12/31 -> 1 | M12: =E12*L12 -> 802654992
A13: AKD Aggressive Fund | E13: 0 | F13: =C13/$E$14 -> 0 | G13: =D24*0.7 -> 700000000 | H13: =E13/$E$14 -> 0 | I13: 31 | J13: 0 | K13: =C13/SUM($E$2:$E$13)*J13 -> 0
A14: Total Income | C14: =SUM(C2:C12) -> 9338974573 | D14: =SUM(D2:D12) -> 9338974573 | E14: =SUM(E2:E12) -> 9338974573 | F14: =SUM(F2:F12) -> 1 | G14: =SUM(G2:G13) -> 9338974573 | H14: =SUM(H2:H12) -> 1 | K14: =SUM(K2:K12) -> 53.743968 | M14: =SUM(M2:M12) -> 9338974573
E15: =E14-D14 -> 0
C16: =C2-B2 -> 57231438 | D16: =SUM(D2:D4) -> 3019147450
B17: Finance Cost
B18: =10.63%-C18 -> 0.1058 | C18: 0.0005 | K18: 1300 | L18: 0.1005 | M18: =L18*K18 -> 130.65
K19: 1238 | L19: 0.1075 | M19: =L19*K19 -> 133.085
C20: Funds Available | D20: =D5+D6+D7 -> 3083525942 | I20: bench | K20: 1238 | L20: =B18 -> 0.1058 | M20: =L20*K20 -> 130.9804
C21: Funds in Samba for operations | D21: =D20-D22 -> 83525942 | E21: (will be moved to Faysal in this week) | L21: =L19-L20 -> 0.0017 | M21: =M18+M19-M20 -> 132.7546
B22: Currently | C22: Placement in Faysal | D22: 3000000000 | M22: =M21/K18 -> 0.10211892
C23: Faysal Saving Account @ 10.25% | D23: 2000000000 | M23: =M22-10.38% -> -0.0016810769
C24: Allocation Available | D24: =D22-D23 -> 1000000000
D26: % to Total Portfolio
A27: Exposure in Alfalah | B27: Current | C27: =G9+G10 -> 1133646189 | D27: =C27/G14 -> 0.12138872 | I27: 2019-20 (12m) | J27: 2020-21 (12m) | K27: 2021-22 (12m) | L27: 2022-23 (12m) | M27: 2023-24 (12m) | N27: 2024-25 (12m) | O27: July-Nov 2025 (5m)
B28: Additional Investment | C28: =C27+G11 -> 1433646189 | D28: =C28/G14 -> 0.15351216 | I28: 13066 | J28: 16694 | K28: 24891 | L28: 52779 | M28: 37386 | N28: 48905 | O28: 5167
I29: 83 | J29: 104 | K29: 140 | L29: 213 | M29: 132 | N29: 175 | O29: 18
I30: 158 | J30: 160 | K30: 177 | L30: 248 | M30: 283 | N30: 279 | O30: 282

Sheet Post MPC Allocation Strategy
B2: Qtr End | C2: =C3+90 -> 46199
B3: Date | C3: =TODAY() -> 46109 | K3: =B9 -> NIT Income Fund
B4: Allocation Available (PKR'Mn) | C4: 3000 | K4: Asset Classes | L4: Allocation % | M4: Amount (PKR) | N4: Rate of Profit | O4: WAM
K5: Govt Securities (Treasury Bills) | L5: 0.0988 | M5: 242197200 | N5: 0.1 | O5: 118
B6: Particular | C6: % of Allocation | D6: Rate | E6: Maturity | F6: Amount (PKR'Mn) | G6: Interest Earned | K6: Govt Securities (PIBs Fixed) | L6: 0.0769 | M6: 188310300 | N6: 0.0998 | O6: 460
B7: Faysal Saving | C7: =F7/$F$13 -> 0 | D7: 0.102 | E7: 0 | F7: 0 | G7: =F7*(D7*($C$2-$C$3)/365) -> 0 | K7: TFCs / Sukuks | L7: 0.4285 | M7: 1049894942 | N7: 0.1231 | O7: 839
A8: AM1 | B8: Alfalah Income Multiplier Fund | C8: =F8/$F$13 -> 0.2173913 | D8: 0.1075 | E8: 45 | F8: 500 | G8: =F8*(D8*(90/365)) -> 13.253425 | K8: Commercial Paper | L8: 0.0197 | M8: 48264706 | N8: 0.1183 | O8: 50
A9: AM1 | B9: NIT Income Fund | C9: =F9/$F$13 -> 0.34782609 | D9: 0.1094 | E9: 382 | F9: 800 | G9: =F9*(D9*($C$2-$C$3)/365) -> 21.580274 | K9: Cash | L9: 0.3601 | M9: 882362185 | N9: 0.112 | O9: 1
B10: MTB (6 Months) | C10: =F10/$F$13 -> 0 | D10: 0.1029 | E10: 180 | F10: 0 | G10: =F10*(D10*($C$2-$C$3)/365) -> 0 | I10: =I20/F20 -> 0 | J10: =H20/F20 -> 0.024152055 | K10: Other Assets | L10: 0.016 | M10: 39234284 | N10: 0
B11: MTB (9 Months) | C11: =F11/$F$13 -> 0.2173913 | D11: 0.1037 | E11: 270 | F11: 500 | G11: =F11*(D11*($C$2-$C$3)/365) -> 12.784932 | I11: =I10*365/180 -> 0 | J11: =J10*365/180 -> 0.048975 | L11: =SUM(L5:L10) -> 1 | M11: =SUM(M5:M10) -> 2450263617 | N11: 0.113 | O11: =SUM(O5:O10) -> 1468
B12: MTB (12 Months) | C12: =F12/$F$13 -> 0.2173913 | D12: 0.1035 | E12: 365 | F12: 500 | G12: =F12*(D12*($C$2-$C$3)/365) -> 12.760274
B13: Total | C13: =SUM(C7:C12) -> 1 | F13: =SUM(F7:F12) -> 2300 | G13: =SUM(G7:G12)+F171 -> 60.378904
J14: =H20/F20 -> 0.024152055 | K14: =B8 -> Alfalah Income Multiplier Fund
F15: =F8+F11+F12 -> 1500 | J15: =J14*365/180 -> 0.048975 | K15: Asset Allocation (% of Net Assets) | L15: 46042
B16: Avg return | D16: =(G13/F13)*365/($C$2-$C$3) -> 0.10646522 | K16: T-bills | L16: 0
B17: Benchmark (3MK-1%) | D17: =10.5%-1% -> 0.095 | K17: PIBs Fixed | L17: 0.0707
B18: Alpha | D18: =D16-D17 -> 0.011465217 | K18: TFCs/Sukuk/CPs | L18: 0.1633
G19: Gross Return | H19: 0.25 | K19: Ijarah | L19: 0.0099
B20: Daewoo Sukuk | D20: =10.56%+2.5% -> 0.1306 | E20: 180 | F20: 275 | G20: =F20*((D20/365)*90) -> 8.8557534 | H20: =G20-(G20*H19) -> 6.6418151 | K20: PIBs Flaoter | L20: 0.015
K21: Ready/Future | L21: 0.1889
D22: 0.1025 | E22: 180 | F22: 300 | G22: =F22*((D22/365)*E22) -> 15.164384 | J22: =G22*0.75 -> 11.373288 | K22: Clean Placements | L22: 0
D23: =D20-D22 -> 0.0281 | G23: =G20-G22 -> -6.3086301 | J23: =G22-J22 -> 3.7910959 | K23: MTS | L23: 0.1586
B24: Total | F24: =F20+F8+F9+F12+F11 -> 2575 | G24: =G20+G8+G9+G12+G11 -> 69.234658 | K24: Cash | L24: 0.3861
D25: Average Return | F25: =(G24/F24)*365/($C$2-$C$3) -> 0.10904272 | K25: Others | L25: 0.0075
D26: Alpha | F26: =F25-D17 -> 0.014042718
B28: Fund Allocation | C28: Rate | D28: Amount (PKR'Mn)
B29: Alfalah Income Multiplier Fund | C29: 0.1075 | D29: 500 | E29: =D29*C29*3/12 -> 13.4375
B30: 9 Months Treasury Bill | C30: =D11 -> 0.1037 | D30: =F11 -> 500 | E30: =D30*C30*3/12 -> 12.9625
B31: 12 Months Treasury Bill | C31: =D12 -> 0.1035 | D31: 500 | E31: =D31*C31*3/12 -> 12.9375

Sheet Dashboard
E10: * adjusted for WHT on debt instruments
E53: Returns on Banks, COIs, and Sukuks are net of WHT.

Sheet WoW Positions
B6: Instrument | C6: Cost of Placement | D6: Past Week | E6: Current Week | F6: Gain/Loss | G6: 1 Day Returns | H6: 15 Day Returns | I6: 30 Day Returns | J6: 90 Day Returns | K6: 7 Day NAV | L6: NAVs | M6: Number of Units | N6: Date of Placement | O6: Date of Maturity | P6: Weekly Yield | Q6: Rate | R6: Tax Adjusted Rate - 1 Day | S6: Gross Expectation | T6: Tax Adjusted Rate - 30 Day | U6: Days to Maturity | V6: Remaining Days | W6: Concentration (%) | X6: PVBP | Y6: Modified Duration | Z6: Convexity | AA6: Tenor | AB6: Secondary Yields | AC6: Dirty Pricing | AD6: Date
B7: MTBs (1Y) | C7: 1999988012 | D7: =C7*Q7/365*(IF(N7<$AD$7-7,($AD$7-N7-7),($AD$7-N7)))+C7 -> 2123393300 | E7: =C7*Q7/365*($AD$7-N7)+C7 -> 2127566425 | F7: =E7-D7 -> 4173125.7 | N7: 45895 | O7: 46240 | P7: =(E7-D7)/C7*365/7 -> 0.1088 | Q7: 0.1088 | R7: =S7 -> 0.1088 | S7: =P7 -> 0.1088 | T7: =S7 -> 0.1088 | U7: =O7-N7 -> 345 | V7: =O7-$AD$7 -> 131 | W7: =C7/$C$21 -> 0.2140575 | X7: =(V7/365)/(1+Q7)*E7*0.0001 -> 68866.552 | Y7: =(V7/365)/(1+Q7) -> 0.32368697 | Z7: =(V7/365)^2/(1+Q7)^2 -> 0.10477325 | AA7: 1Y | AB7: {=xlookup(AA7,'PKRV Rates'!$A$2:$A$21,'PKRV Rates'!$B$2:$B$21,0,1)/100} -> 0.1163 | AC7: =C7*(((1+(Q7*U7/365))/(1+(AB7*V7/365)))) -> 2117286781 | AD7: =today() -> 46109
B8: MTBs (6M) | C8: 474182500 | D8: =C8*Q8/365*(IF(N8<$AD$7-7,($AD$7-N8-7),($AD$7-N8)))+C8 -> 4.88369e+08 | E8: =C8*Q8/365*($AD$7-N8)+C8 -> 4.8936206e+08 | F8: =E8-D8 -> 993055.08 | N8: 46002 | O8: 46184 | P8: =(E8-D8)/C8*365/7 -> 0.1092 | Q8: 0.1092 | R8: =S8 -> 0.1092 | S8: =P8 -> 0.1092 | T8: =S8 -> 0.1092 | U8: =O8-N8 -> 182 | V8: =O8-$AD$7 -> 75 | W8: =C8/$C$21 -> 0.050751465 | X8: =(V8/365)/(1+Q8)*E8*0.0001 -> 9065.4388 | Y8: =(V8/365)/(1+Q8) -> 0.18525014 | Z8: =(V8/365)^2/(1+Q8)^2 -> 0.034317613 | AA8: 6M | AB8: {=xlookup(AA8,'PKRV Rates'!$A$2:$A$21,'PKRV Rates'!$B$2:$B$21,0,1)/100} -> 0.1136 | AC8: =C8*(((1+(Q8*U8/365))/(1+(AB8*V8/365)))) -> 4.8859688e+08 | AD8: =AD7 -> 46109
B9: MTBs (1Y) | C9: =1199982431+112795631 -> 1312778062 | D9: =C9*Q9/365*(IF(N9<$AD$7-7,($AD$7-N9-7),($AD$7-N9)))+C9 -> 1324161466 | E9: =C9*Q9/365*($AD$7-N9)+C9 -> 1326817594 | F9: =E9-D9 -> 2656127.7 | N9: 46072 | O9: =N9+364 -> 46436 | P9: =(E9-D9)/C9*365/7 -> 0.1055 | Q9: 0.1055 | R9: =S9 -> 0.1055 | S9: =P9 -> 0.1055 | T9: =S9 -> 0.1055 | U9: =O9-N9 -> 364 | V9: =O9-$AD$7 -> 327 | W9: =C9/$C$21 -> 0.14050584 | X9: =(V9/365)/(1+Q9)*E9*0.0001 -> 107524.48 | Y9: =(V9/365)/(1+Q9) -> 0.81039386 | Z9: =(V9/365)^2/(1+Q9)^2 -> 0.65673821 | AA9: 1Y | AB9: {=xlookup(AA9,'PKRV Rates'!$A$2:$A$21,'PKRV Rates'!$B$2:$B$21,0,1)/100} -> 0.1163 | AC9: =C9*(((1+(Q9*U9/365))/(1+(AB9*V9/365)))) -> 1313989441 | AD9: =AD8 -> 46109
B10: MTBs (1Y) | C10: 384022350 | D10: =C10*Q10/365*(IF(N10<$AD$7-7,($AD$7-N10-7),($AD$7-N10)))+C10 -> 3.8582357e+08 | E10: =C10*Q10/365*($AD$7-N10)+C10 -> 3.8661161e+08 | F10: =E10-D10 -> 788034.9 | N10: 46086 | O10: =N10+364 -> 46450 | P10: =(E10-D10)/C10*365/7 -> 0.107 | Q10: 0.107 | R10: =S10 -> 0.107 | S10: =P10 -> 0.107 | T10: =S10 -> 0.107 | U10: =O10-N10 -> 364 | V10: =O10-$AD$7 -> 341 | W10: =C10/$C$21 -> 0.041101679 | X10: =(V10/365)/(1+Q10)*E10*0.0001 -> 32627.874 | Y10: =(V10/365)/(1+Q10) -> 0.84394451 | Z10: =(V10/365)^2/(1+Q10)^2 -> 0.71224234 | AA10: 1Y | AB10: {=xlookup(AA10,'PKRV Rates'!$A$2:$A$21,'PKRV Rates'!$B$2:$B$21,0,1)/100} -> 0.1163 | AC10: =C10*(((1+(Q10*U10/365))/(1+(AB10*V10/365)))) -> 3.8334827e+08 | AD10: =AD9 -> 46109
B11: MTBs (1Y) | C11: 451587500 | D11: =C11*Q11/365*(IF(N11<$AD$7-7,($AD$7-N11-7),($AD$7-N11)))+C11 -> 4.5370959e+08 | E11: =C11*Q11/365*($AD$7-N11)+C11 -> 4.54638e+08 | F11: =E11-D11 -> 928414.41 | N11: 46086 | O11: =N11+364 -> 46450 | P11: =(E11-D11)/C11*365/7 -> 0.1072 | Q11: 0.1072 | R11: =S11 -> 0.1072 | S11: =P11 -> 0.1072 | T11: =S11 -> 0.1072 | U11: =O11-N11 -> 364 | V11: =O11-$AD$7 -> 341 | W11: =C11/$C$21 -> 0.048333136 | X11: =(V11/365)/(1+Q11)*E11*0.0001 -> 38361.994 | Y11: =(V11/365)/(1+Q11) -> 0.84379207 | Z11: =(V11/365)^2/(1+Q11)^2 -> 0.71198505 | AA11: 1Y | AB11: {=xlookup(AA11,'PKRV Rates'!$A$2:$A$21,'PKRV Rates'!$B$2:$B$21,0,1)/100} -> 0.1163 | AC11: =C11*(((1+(Q11*U11/365))/(1+(AB11*V11/365)))) -> 4.5087607e+08 | AD11: =AD10 -> 46109
B12: MTBs (1Y) | C12: 451709500 | D12: =C12*Q12/365*(IF(N12<$AD$7-7,($AD$7-N12-7),($AD$7-N12)))+C12 -> 4.538381e+08 | E12: =C12*Q12/365*($AD$7-N12)+C12 -> 4.5476937e+08 | F12: =E12-D12 -> 931264.11 | N12: 46086 | O12: =N12+364 -> 46450 | P12: =(E12-D12)/C12*365/7 -> 0.1075 | Q12: =10.75% -> 0.1075 | R12: =S12 -> 0.1075 | S12: =P12 -> 0.1075 | T12: =S12 -> 0.1075 | U12: =O12-N12 -> 364 | V12: =O12-$AD$7 -> 341 | W12: =C12/$C$21 -> 0.048346194 | X12: =(V12/365)/(1+Q12)*E12*0.0001 -> 38362.684 | Y12: =(V12/365)/(1+Q12) -> 0.8435635 | Z12: =(V12/365)^2/(1+Q12)^2 -> 0.71159938 | AA12: 1Y | AB12: {=xlookup(AA12,'PKRV Rates'!$A$2:$A$21,'PKRV Rates'!$B$2:$B$21,0,1)/100} -> 0.1163 | AC12: =C12*(((1+(Q12*U12/365))/(1+(AB12*V12/365)))) -> 4.5111977e+08 | AD12: =AD11 -> 46109
B13: Faysal Bank | C13: 229894920 | D13: =C13 -> 229894920 | E13: =D13 -> 229894920 | F13: =D13*Q13*7/365*(1-20%) -> 361533.38 | P13: =F13/D13*365/7 -> 0.082 | Q13: 0.1025 | R13: =S13 -> 0.082 | S13: =Q13*0.8 -> 0.082 | T13: =S13 -> 0.082 | U13: 1 | V13: 1 | W13: =C13/$C$21 -> 0.024605514 | X13: =(V13/365)/(1+Q13)*E13*0.0001 -> 57.12917 | Y13: =(V13/365)/(1+Q13) -> 0.0024850123 | Z13: =(V13/365)^2/(1+Q13)^2 -> 6.175286e-06 | AC13: =E13 -> 229894920 | AD13: =AD12 -> 46109
B14: Samba Bank | C14: 0 | D14: =C14 -> 0 | E14: =D14 -> 0 | F14: =D14*Q14*7/365*(1-20%) -> 0 | O14: 46118 | P14: =Q14*(1-0.2) -> 0.082 | Q14: 0.1025 | R14: =S14 -> 0.082 | S14: =Q14*0.8 -> 0.082 | T14: =S14 -> 0.082 | U14: =V14 -> 9 | V14: =O14-AD7 -> 9 | W14: =C14/$C$21 -> 0 | X14: =(V14/365)/(1+Q14)*E14*0.0001 -> 0 | Y14: =(V14/365)/(1+Q14) -> 0.02236511 | Z14: =(V14/365)^2/(1+Q14)^2 -> 0.00050019816 | AC14: =E14 -> 0 | AD14: =AD13 -> 46109
B15: COI | C15: 1300000000 | D15: =(C15*Q15/365*(IF(N15<$AD$7-7,($AD$7-N15-7),($AD$7-N15)))*(1-20%))+C15 -> 1305727123 | E15: =(C15*Q15/365*($AD$7-N15)*(1-20%))+C15 -> 1307731616 | F15: =E15-D15 -> 2004493.2 | N15: 46082 | O15: 46112 | P15: =(E15-D15)/C15*365/7 -> 0.0804 | Q15: 0.1005 | R15: =S15 -> 0.0804 | S15: =Q15*0.8 -> 0.0804 | T15: =S15 -> 0.0804 | U15: 30 | V15: =O15-AD7 -> 3 | W15: =C15/$C$21 -> 0.13913821 | X15: =(V15/365)/(1+Q15)*E15*0.0001 -> 976.69051 | Y15: =(V15/365)/(1+Q15) -> 0.0074685853 | Z15: =(V15/365)^2/(1+Q15)^2 -> 5.5779766e-05 | AC15: =E15 -> 1307731616 | AD15: =AD14 -> 46109
B16: Alfalah Government Securities Fund Plan II | C16: 827608440 | D16: =M16*K16 -> 8.3479721e+08 | E16: =L16*M16 -> 8.3542376e+08 | F16: =E16-D16 -> 626551.65 | G16: {=xlookup($B16,'MUFAP Data'!$C:$C,'MUFAP Data'!H:H,0,0)/100} -> 0.0781 | H16: {=xlookup($B16,'MUFAP Data'!$C:$C,'MUFAP Data'!I:I,0,0)/100} -> -0.0193 | I16: {=xlookup($B16,'MUFAP Data'!$C:$C,'MUFAP Data'!J:J,0,0)/100} -> -0.2778 | J16: {=xlookup($B16,'MUFAP Data'!$C:$C,'MUFAP Data'!K:K,0,0)/100} -> 0.023 | K16: 105.79 | L16: {=xlookup($B16,'MUFAP Data'!$C:$C,'MUFAP Data'!G:G,0,0)} -> 105.8694 | M16: 7891078.7 | P16: =(L16/K16-1)*365/7 -> 0.039135484 | Q16: 0.07 | R16: =G16 -> 0.0781 | S16: =Q16 -> 0.07 | T16: =I16 -> -0.2778 | U16: =0.78*365 -> 284.7 | V16: =1*U16 -> 284.7 | W16: =C16/$C$21 -> 0.088578429 | X16: =(V16/365)/(1+Q16)*E16*0.0001 -> 60900.05 | Y16: =(V16/365)/(1+Q16) -> 0.72897196 | Z16: =(V16/365)^2/(1+Q16)^2 -> 0.53140012 | AC16: =E16 -> 8.3542376e+08 | AD16: =AD15 -> 46109
B17: Alfalah MTS Fund | C17: =D17 -> 3.1337318e+08 | D17: =M17*K17 -> 3.1337318e+08 | E17: =L17*M17 -> 3.1407429e+08 | F17: =E17-D17 -> 701109.89 | G17: {=xlookup($B17,'MUFAP Data'!$C:$C,'MUFAP Data'!H:H,0,0)/100} -> 0.1124 | H17: {=xlookup($B17,'MUFAP Data'!$C:$C,'MUFAP Data'!I:I,0,0)/100} -> 0.0949 | I17: {=xlookup($B17,'MUFAP Data'!$C:$C,'MUFAP Data'!J:J,0,0)/100} -> 0.0876 | J17: {=xlookup($B17,'MUFAP Data'!$C:$C,'MUFAP Data'!K:K,0,0)/100} -> 0.0945 | K17: 112.01 | L17: {=xlookup($B17,'MUFAP Data'!$C:$C,'MUFAP Data'!G:G,0,0)} -> 112.2606 | M17: 2797725 | P17: =(L17/K17-1)*365/7 -> 0.11665923 | Q17: 0.07 | R17: =G17 -> 0.1124 | S17: =Q17 -> 0.07 | T17: =I17 -> 0.0876 | U17: 1 | V17: =1*U17 -> 1 | W17: =C17/$C$21 -> 0.033540141 | X17: =(V17/365)/(1+Q17)*E17*0.0001 -> 80.418458 | Y17: =(V17/365)/(1+Q17) -> 0.0025604916 | Z17: =(V17/365)^2/(1+Q17)^2 -> 6.5561173e-06 | AC17: =E17 -> 3.1407429e+08 | AD17: =AD16 -> 46109
B18: Alfalah GHP Income Multiplier Fund | C18: =D18 -> 5.029355e+08 | D18: =M18*K18 -> 5.029355e+08 | E18: =L18*M18 -> 5.0359115e+08 | F18: =E18-D18 -> 655651.33 | G18: {=xlookup($B18,'MUFAP Data'!$C:$C,'MUFAP Data'!H:H,0,0)/100} -> 0.1912 | H18: {=xlookup($B18,'MUFAP Data'!$C:$C,'MUFAP Data'!I:I,0,0)/100} -> 0.0561 | I18: {=xlookup($B18,'MUFAP Data'!$C:$C,'MUFAP Data'!J:J,0,0)/100} -> 0.0854 | J18: {=xlookup($B18,'MUFAP Data'!$C:$C,'MUFAP Data'!K:K,0,0)/100} -> 0.0626 | K18: 62.21 | L18: {=xlookup($B18,'MUFAP Data'!$C:$C,'MUFAP Data'!G:G,0,0)} -> 62.2911 | M18: 8084480 | P18: =(L18/K18-1)*365/7 -> 0.06797598 | Q18: 0.07 | R18: =G18 -> 0.1912 | S18: =Q18 -> 0.07 | T18: =I18 -> 0.0854 | U18: =0.22*365 -> 80.3 | V18: =1*U18 -> 80.3 | W18: =C18/$C$21 -> 0.053828881 | X18: =(V18/365)/(1+Q18)*E18*0.0001 -> 10354.211 | Y18: =(V18/365)/(1+Q18) -> 0.20560748 | Z18: =(V18/365)^2/(1+Q18)^2 -> 0.042274434 | AC18: =E18 -> 5.0359115e+08 | AD18: =AD17 -> 46109
B19: MCB Investment Savings Plan I | C19: =D19 -> 8.2014783e+08 | D19: =M19*K19 -> 8.2014783e+08 | E19: =L19*M19 -> 8.2213926e+08 | F19: =E19-D19 -> 1991432.5 | G19: {=xlookup($B19,'MUFAP Data'!$C:$C,'MUFAP Data'!H:H,0,0)/100} -> 0.1201 | H19: {=xlookup($B19,'MUFAP Data'!$C:$C,'MUFAP Data'!I:I,0,0)/100} -> 0.0999 | I19: {=xlookup($B19,'MUFAP Data'!$C:$C,'MUFAP Data'!J:J,0,0)/100} -> 0.0931 | J19: {=xlookup($B19,'MUFAP Data'!$C:$C,'MUFAP Data'!K:K,0,0)/100} -> 0.0992 | K19: 108.89 | L19: {=xlookup($B19,'MUFAP Data'!$C:$C,'MUFAP Data'!G:G,0,0)} -> 109.1544 | M19: 7531893 | P19: =(L19/K19-1)*365/7 -> 0.12661008 | Q19: 0.07 | R19: =G19 -> 0.1201 | S19: =Q19 -> 0.07 | T19: =I19 -> 0.0931 | U19: 1 | V19: =1*U19 -> 1 | W19: =C19/$C$21 -> 0.087779924 | X19: =(V19/365)/(1+Q19)*E19*0.0001 -> 210.50807 | Y19: =(V19/365)/(1+Q19) -> 0.0025604916 | Z19: =(V19/365)^2/(1+Q19)^2 -> 6.5561173e-06 | AC19: =E19 -> 8.2213926e+08 | AD19: =AD18 -> 46109
B20: Daewoo Short Term SUKUK | C20: 275000000 | D20: =(C20*Q20/365*(IF(N20<$AD$7-7,($AD$7-N20-7),($AD$7-N20)))*(1-25%))+C20 -> 2.7677522e+08 | E20: =(C20*Q20*($AD$7-N20)/365*(1-20%))+C20 -> 2.7744586e+08 | F20: =E20-D20 -> 670638.36 | N20: 46078 | O20: =N20+180 -> 46258 | P20: =(E20-D20)/C20*365/7 -> 0.12716 | Q20: 0.1309 | R20: =S20 -> 0.12716 | S20: =P20 -> 0.12716 | T20: =S20 -> 0.12716 | U20: =O20-N20 -> 180 | V20: =O20-$AD$7 -> 149 | W20: =C20/$C$21 -> 0.029433083 | X20: =(V20/365)/(1+Q20)*E20*0.0001 -> 10014.919 | Y20: =(V20/365)/(1+Q20) -> 0.36096841 | Z20: =(V20/365)^2/(1+Q20)^2 -> 0.1302982 | AC20: =E20 -> 2.7744586e+08 | AD20: =AD19 -> 46109
B21: Total | C21: =SUM(C7:C20) -> 9343227791 | D21: =SUM(D7:D20) -> 9512946015 | E21: =SUM(E7:E20) -> 9530065914 | F21: =SUM(F7:F20) -> 17481432 | P21: =sumproduct(P7:P20,W7:W20) -> 0.097530586 | Q21: =sumproduct(Q7:Q20,$W$7:$W$20) -> 0.097250452 | R21: =sumproduct(R7:R20,$W$7:$W$20) -> 0.1069007 | S21: =sumproduct(S7:S20,$W$7:$W$20) -> 0.093839281 | T21: =sumproduct(T7:T20,$W$7:$W$20) -> 0.066478691 | U21: =sumproduct(U7:U20,W7:W20) -> 223.54178 | V21: =sumproduct(V7:V20,W7:W20) -> 159.26623 | W21: =SUM(W7:W20) -> 1 | X21: =SUM(X7:X20) -> 377402.95 | Y21: =sumproduct(Y7:Y20,$W$7:$W$20) -> 0.39648232 | Z21: =sumproduct(Z7:Z20,$W$7:$W$20) -> 0.26772463 | AC21: =SUM(AC7:AC20) -> 9495518070
B22: Liabilities
B23: Borrowing | C23: 1238000000 | D23: =C23 -> 1238000000 | E23: =D23 -> 1238000000 | F23: =E23*7/365*Q23 -> -2511952.9 | N23: =N15 -> 46082 | O23: =O15 -> 46112 | Q23: -0.1058 | AC23: =C23 -> 1238000000
F24: =F21+F23 -> 14969479 | P24: =(F21+F23)/(C21-C23)*365/7 -> 0.096302218
F25: =F23/7*90 -> -32296537
B26: NAV | D26: =(D21-D23)/D27 -> 82.74946 | E26: =(E21-E23)/E27 -> 82.920659 | AC26: =(AC21-AC23)/AC27 -> 82.575181
B27: NAV Units | D27: =10^8 -> 100000000 | E27: =10^8 -> 100000000 | AC27: =10^8 -> 100000000
E28: =E26/D26-1 -> 0.0020688834 | AC28: =AC26/E26-1 -> -0.0041663736
B31: Benchmark | C31: =C34-1% -> 0.1038
B32: Alpha | C32: =T21-C31 -> -0.037321309
B34: 3MK | C34: =IFERROR(__xludf.DUMMYFUNCTION("ai(""Write today's 3 month KIBOR in the active cell"",C36)"),"11.38%") -> 11.38%

Sheet Monthly Stakeholder Update
A2: Mutual Funds | B2: Begining Nav | C2: Latest Nav | D2: Units | E2: Begining Value | F2: Latest Value | G2: Monthly Return | H2: Mufap 30 day returns
A3: Alfalah Government Securities Fund Plan II | B3: 105.97 | C3: 105.95 | D3: ='WoW Positions'!M16 -> 7891078.7 | E3: =B3*D3 -> 8.3621761e+08 | F3: =C3*D3 -> 8.3605979e+08 | G3: =(F3/E3-1)*365/30 -> -0.0022962474 | H3: 0.002
A4: Alfalah MTS Fund | B4: 111.41 | C4: 112.23 | D4: ='WoW Positions'!M17 -> 2797725 | E4: =B4*D4 -> 3.1169454e+08 | F4: =C4*D4 -> 3.1398868e+08 | G4: =(F4/E4-1)*365/30 -> 0.089549113 | H4: 0.0968
A5: Alfalah GHP Income Multiplier Fund | B5: 62.07 | C5: 62.28 | D5: ='WoW Positions'!M18 -> 8084480 | E5: =B5*D5 -> 5.0180367e+08 | F5: =C5*D5 -> 5.0350141e+08 | G5: =(F5/E5-1)*365/30 -> 0.041163203 | H5: 0.042
A6: MCB Investment Savings Plan I | B6: 108.3 | C6: 109.13 | D6: ='WoW Positions'!M19 -> 7531893 | E6: =B6*D6 -> 8.1570401e+08 | F6: =C6*D6 -> 8.2195548e+08 | G6: =(F6/E6-1)*365/30 -> 0.093244075 | H6: 0.1
A7: MTBs | B7: Cost | C7: Yield | D7: Days to Maturity | E7: Remaining days | F7: Days Elapsed | G7: Accrued Interest | H7: Total Value
A8: MTBs (1Y) | B8: ='WoW Positions'!C7 -> 1999988012 | C8: ='WoW Positions'!Q7 -> 0.1088 | D8: ='WoW Positions'!U7 -> 345 | E8: ='WoW Positions'!V7 -> 131 | F8: =D8-E8 -> 214 | G8: =B8*C8*F8/365 -> 1.2757841e+08 | H8: =B8+G8 -> 2127566425
A9: MTBs (6M) | B9: ='WoW Positions'!C8 -> 474182500 | C9: ='WoW Positions'!Q8 -> 0.1092 | D9: ='WoW Positions'!U8 -> 182 | E9: ='WoW Positions'!V8 -> 75 | F9: =D9-E9 -> 107 | G9: =B9*C9*F9/365 -> 15179556 | H9: =B9+G9 -> 4.8936206e+08
A10: MTBs (1Y) | B10: ='WoW Positions'!C9 -> 1312778062 | C10: ='WoW Positions'!Q9 -> 0.1055 | D10: ='WoW Positions'!U9 -> 364 | E10: ='WoW Positions'!V9 -> 327 | F10: =D10-E10 -> 37 | G10: =B10*C10*F10/365 -> 14039532 | H10: =B10+G10 -> 1326817594
A11: MTBs (1Y) | B11: ='WoW Positions'!C10 -> 384022350 | C11: ='WoW Positions'!Q10 -> 0.107 | D11: ='WoW Positions'!U10 -> 364 | E11: ='WoW Positions'!V10 -> 341 | F11: =D11-E11 -> 23 | G11: =B11*C11*F11/365 -> 2589257.5 | H11: =B11+G11 -> 3.8661161e+08
A12: MTBs (1Y) | B12: ='WoW Positions'!C11 -> 451587500 | C12: ='WoW Positions'!Q11 -> 0.1072 | D12: ='WoW Positions'!U11 -> 364 | E12: ='WoW Positions'!V11 -> 341 | F12: =D12-E12 -> 23 | G12: =B12*C12*F12/365 -> 3050504.5 | H12: =B12+G12 -> 4.54638e+08
A13: MTBs (1Y) | B13: ='WoW Positions'!C12 -> 451709500 | C13: ='WoW Positions'!Q12 -> 0.1075 | D13: ='WoW Positions'!U12 -> 364 | E13: ='WoW Positions'!V12 -> 341 | F13: =D13-E13 -> 23 | G13: =B13*C13*F13/365 -> 3059867.8 | H13: =B13+G13 -> 4.5476937e+08
A14: COI | B14: Principal | C14: Rate | D14: Days | E14: End Value | F14: Accrued Interest
B15: 1300000000 | C15: 0.1005 | D15: 30 | E15: =B15+(B15*C15*D15/365) -> 1310738356 | F15: =E15-B15 -> 10738356
A16: Bank Placements

Sheet WoW Archive
B2: No calculations - just values to be pasted here on a WoW basis.
B4: Instrument | C4: Cost of Placement | D4: Past Week | E4: Current Week | F4: Gain/Loss | G4: 1 Day Returns | H4: 15 Day Returns | I4: 30 Day Returns | J4: 90 Day Returns | K4: 7 Day NAV | L4: NAVs | M4: Number of Units | N4: Date of Placement | O4: Date of Maturity | P4: Weekly Yield | Q4: Rate | R4: Tax Adjusted Rate | S4: Days to Maturity | T4: Remaining Days | U4: Concentration (%) | V4: PVBP | W4: Modified Duration | X4: Convexity | Y4: Date
B5: MTBs (1Y) | C5: 1999988012 | D5: 2.1204125e+09 | E5: 2.1245856e+09 | F5: 4173125.7 | N5: 45895 | O5: 46240 | P5: 0.1088 | Q5: 0.1088 | R5: 0.1088 | S5: 345 | T5: 136 | U5: 0.21354359 | V5: 71394.879 | W5: 0.33604143 | X5: 0.11292384 | Y5: 46104
B6: MTBs (6M) | C6: 474182500 | D6: 4.8765968e+08 | E6: 4.8865273e+08 | F6: 993055.08 | N6: 46002 | O6: 46184 | P6: 0.1092 | Q6: 0.1092 | R6: 0.1092 | S6: 182 | T6: 80 | U6: 0.05062962 | V6: 9655.7851 | W6: 0.19760015 | X6: 0.039045818 | Y6: 46104
B7: MTBs (1Y) | C7: 1312778062 | D7: 1.3222642e+09 | E7: 1.3249204e+09 | F7: 2656127.7 | N7: 46072 | O7: 46436 | P7: 0.1055 | Q7: 0.1055 | R7: 0.1055 | S7: 364 | T7: 332 | U7: 0.14016851 | V7: 109012.49 | W7: 0.8227852 | X7: 0.67697549 | Y7: 46104
B8: MTBs (1Y) | C8: 384022350 | D8: 3.8526069e+08 | E8: 3.8604873e+08 | F8: 788034.9 | N8: 46086 | O8: 46450 | P8: 0.107 | Q8: 0.107 | R8: 0.107 | S8: 364 | T8: 346 | U8: 0.041003001 | V8: 33058.088 | W8: 0.85631907 | X8: 0.73328234 | Y8: 46104
B9: MTBs (1Y) | C9: 451587500 | D9: 4.5304644e+08 | E9: 4.5397485e+08 | F9: 928414.41 | N9: 46086 | O9: 46450 | P9: 0.1072 | Q9: 0.1072 | R9: 0.1072 | S9: 364 | T9: 346 | U9: 0.048217096 | V9: 38867.71 | W9: 0.85616438 | X9: 0.73301745 | Y9: 46104
B10: MTBs (1Y) | C10: 451709500 | D10: 4.5317292e+08 | E10: 4.5410418e+08 | F10: 931264.11 | N10: 46086 | O10: 46450 | P10: 0.1075 | Q10: 0.1075 | R10: 0.1075 | S10: 364 | T10: 346 | U10: 0.048230123 | V10: 38868.251 | W10: 0.85593247 | X10: 0.73262039 | Y10: 46104
B11: Faysal Bank | C11: 253133899 | D11: 253133899 | E11: 253133899 | F11: 398079.06 | P11: 0.082 | Q11: 0.1025 | R11: 0.082 | S11: 1 | T11: 1 | U11: 0.027027722 | V11: 62.904084 | W11: 0.0024850123 | X11: 6.175286e-06 | Y11: 46104
B12: Samba Bank | C12: 0 | D12: 0 | E12: 0 | F12: 0 | O12: 46118 | P12: 0 | Q12: 0.105 | R12: 0.084 | S12: 14 | T12: 14 | U12: 0 | V12: 0 | W12: 0.034711461 | X12: 0.0012048855 | Y12: 46104
B13: COI | C13: 1300000000 | D13: 1.3042953e+09 | E13: 1.3062998e+09 | F13: 2004493.2 | N13: 46082 | O13: 46112 | P13: 0.0804 | Q13: 0.1005 | R13: 0.0804 | S13: 30 | T13: 8 | U13: 0.13880416 | V13: 2601.6565 | W13: 0.019916227 | X13: 0.00039665611 | Y13: 46104
B14: Alfalah Government Securities Fund Plan II | C14: 827608440 | D14: 8.3448157e+08 | E14: 8.3493452e+08 | F14: 452947.92 | G14: 0.0796 | H14: -0.0387 | I14: 0.0679 | J14: -0.0648 | K14: 105.75 | L14: 105.8074 | M14: 7891078.7 | P14: 0.0283026 | Q14: 0.03 | R14: 0.03 | S14: 284.7 | T14: 284.7 | U14: 0.088365767 | V14: 63228.051 | W14: 0.75728155 | X14: 0.57347535 | Y14: 46104
B15: Alfalah MTS Fund | C15: 313233291 | D15: 313233291 | E15: 3.1344396e+08 | F15: 210668.69 | G15: 0.1128 | H15: 0.096 | I15: 0.0923 | J15: 0.095 | K15: 111.96 | L15: 112.0353 | M15: 2797725 | P15: 0.035069285 | Q15: 0.03 | R15: 0.03 | S15: 1 | T15: 1 | U15: 0.033444681 | V15: 83.373842 | W15: 0.0026599282 | X15: 7.0752179e-06 | Y15: 46104
B16: Alfalah GHP Income Multiplier Fund | C16: 5.0277381e+08 | D16: 5.0277381e+08 | E16: 5.0303332e+08 | F16: 259511.81 | G16: 0.1953 | H16: 0.0584 | I16: 0.0599 | J16: 0.0552 | K16: 62.19 | L16: 62.2221 | M16: 8084480 | P16: 0.026914065 | Q16: 0.05 | R16: 0.05 | S16: 80.3 | T16: 80.3 | U16: 0.053682383 | V16: 10539.746 | W16: 0.20952381 | X16: 0.043900227 | Y16: 46104
B17: MCB Investment Savings Plan I | C17: 8.1969592e+08 | D17: 8.1969592e+08 | E17: 8.2034592e+08 | F17: 650002.37 | G17: 0.1204 | H17: 0.0998 | I17: 0.0996 | J17: 0.0997 | K17: 108.83 | L17: 108.9163 | M17: 7531893 | P17: 0.041348236 | Q17: 0.05 | R17: 0.05 | S17: 1 | T17: 1 | U17: 0.087520928 | V17: 214.04982 | W17: 0.0026092629 | X17: 6.8082528e-06 | Y17: 46104
B18: Daewoo Short Term SUKUK | C18: 275000000 | D18: 2.7640538e+08 | E18: 2.7705136e+08 | F18: 645982.53 | N18: 46078 | O18: 46258 | P18: 0.122485 | Q18: 0.1309 | R18: 0.1309 | S18: 180 | T18: 154 | U18: 0.029362419 | V18: 10336.272 | W18: 0.37308145 | X18: 0.13918977 | Y18: 46104
B19: Total | C19: 9.3657133e+09 | D19: 9.5258357e+09 | E19: 9.5405293e+09 | F19: 15091707 | P19: 0.0840011 | Q19: 0.089569186 | R19: 0.086225154 | S19: 223.00613 | T19: 162.43469 | U19: 1 | V19: 387923.25 | W19: 0.40703665 | X19: 0.27890207
B20: Liabilities
B21: Borrowing | C21: 1238000000 | D21: 1238000000 | E21: 1238000000 | F21: -2511952.9 | N21: 46082 | O21: 46112 | Q21: -0.1058 | T21: 90
F22: 12579754 | P22: 0.080704661
F23: -32296537
B24: NAV | D24: 82.878357 | E24: 83.025293
B25: NAV Units | D25: 100000000 | E25: 100000000
E26: 0.001772915

Sheet Pivot Table 1

Sheet Daewoo Sukuk
B4: National Credit Guarantee Company Limited
B5: Investments Team | G5: Date: | H5: =TODAY() -> 46109
B7: Proposed Transaction
B8: Placement in Sukuk
B9: Bank/Company/SPV | C9: Amount (PKR'Mn) | D9: Rate | E9: Days | F9: Gross (PKR'Mn) | G9: Tax @ 25% | H9: Net (PKR'Mn)
B10: Daewoo Pakistan Express Bus Service Limited | C10: 275 | D10: =10.56%+2.5% -> 0.1306 | E10: 180 | F10: =C10*(D10*E10/C23) -> 17.711507 | G10: =F10*25% -> 4.4278767 | H10: =F10-G10 -> 13.28363
F11: =F10/C10 -> 0.064405479 | H11: =H10/C10 -> 0.04830411
B12: Annualized Yield | F12: =F11*(365/180) -> 0.1306 | H12: =H11*(365/180) -> 0.09795
B14: Status Quo
B15: Bank/Company/SPV | C15: Amount (PKR'Mn) | D15: Rate | E15: Days | F15: Gross (PKR'Mn) | G15: Tax @ 20% | H15: Net (PKR'Mn)
B16: Faysal Bank Limited | C16: 275 | D16: 0.1025 | E16: 180 | F16: =C16*(D16*E16/C23) -> 13.900685 | G16: =F16*20% -> 2.780137 | H16: =F16-G16 -> 11.120548
F17: =F16/C16 -> 0.050547945 | H17: =H16/C16 -> 0.040438356
B18: Annualized Yield | F18: =F17*(365/180) -> 0.1025 | H18: =H17*(365/180) -> 0.082
B20: Delta (Gross) | C20: =F12-F18 -> 0.0281
B21: Delta (Net) | C21: =H12-H18 -> 0.01595
B23: Period (days) | C23: 365

Sheet IOM-007
B5: National Credit Guarantee Company Limited
B6: Investments Team | G6: Date: | H6: =TODAY() -> 46109
B8: Proposed Transaction
B9: Govt. Security Placement
C10: Placement | D10: Rate | E10: Days | F10: Gross | G10: Tax | H10: Net
B11: 12M MTBs | C11: 1238 | D11: 0.1055 | E11: 90 | F11: =C11*(D11*E11/C24) -> 32.204959 | G11: =F11*15% -> 4.8307438 | H11: =F11-G11 -> 27.374215
F12: =F11/C11 -> 0.026013699 | H12: =H11/C11 -> 0.022111644
B13: Annualized Yield | H13: =H12*(365/E11) -> 0.089675
B15: Status Quo
C16: Placement | D16: Rate | E16: Days | F16: Gross | G16: Tax | H16: Net
B17: Faysal Bank Limited | C17: =C11 -> 1238 | D17: 0.1025 | E17: 90 | F17: =C17*(D17*E17/C24) -> 31.289178 | G17: =F17*20% -> 6.2578356 | H17: =F17-G17 -> 25.031342
F18: =F17/C17 -> 0.025273973 | H18: =H17/C17 -> 0.020219178
B19: Annualized Yield | H19: =H18*(365/E17) -> 0.082
B21: Delta (Gross) | C21: =D11-D17 -> 0.003
B22: Delta (Net) | C22: =H13-H19 -> 0.007675
B24: Period (days) | C24: 365
B25: Note: All amounts mentioned in PKR mn unless stated otherwise.

Sheet IOM-008
B4: National Credit Guarantee Company Limited
B5: Investments Team | G5: Date: | H5: =TODAY() -> 46109
B7: Proposed Transaction
B8: Reverse Repo
C9: Placement | D9: Rate | E9: Days | F9: Gross | G9: Tax | H9: Net
B10: Pak Oman Investment Company | C10: 1000 | D10: 0.105 | E10: 30 | F10: =C10*(D10*E10/C23) -> 8.630137 | G10: =F10*20% -> 1.7260274 | H10: =F10-G10 -> 6.9041096
F11: =F10/C10 -> 0.008630137 | H11: =H10/C10 -> 0.0069041096
B12: Annualized Yield | H12: =H11*(365/E10) -> 0.084
B14: Status Quo
C15: Placement | D15: Rate | E15: Days | F15: Gross | G15: Tax | H15: Net
B16: Faysal Bank Limited | C16: 1000 | D16: 0.1025 | E16: 30 | F16: =C16*(D16*E16/C23) -> 8.4246575 | G16: =F16*20% -> 1.6849315 | H16: =F16-G16 -> 6.739726
F17: =F16/C16 -> 0.0084246575 | H17: =H16/C16 -> 0.006739726
B18: Annualized Yield | H18: =H17*(365/E16) -> 0.082
B20: Delta (Gross) | C20: =D10-D16 -> 0.0025
B21: Delta (Net) | C21: =H12-H18 -> 0.002
B23: Period (days) | C23: 365
B24: Note: All amounts mentioned in PKR mn unless stated otherwise.
B52: National Credit Guarantee Company Limited
B53: Investments Team | G53: Date: | H53: =TODAY() -> 46109
B55: Proposed Transaction
B56: Govt. Security Placement
C57: Placement | D57: Rate | E57: Days | F57: Gross | G57: Tax | H57: Net
B58: 12M MTBs | C58: 1238 | D58: 0.1055 | E58: 90 | F58: =C58*(D58*E58/C71) -> 32.204959 | G58: =F58*15% -> 4.8307438 | H58: =F58-G58 -> 27.374215
F59: =F58/C58 -> 0.026013699 | H59: =H58/C58 -> 0.022111644
B60: Annualized Yield | H60: =H59*(365/E58) -> 0.089675
B62: Status Quo
C63: Placement | D63: Rate | E63: Days | F63: Gross | G63: Tax | H63: Net
B64: Faysal Bank Limited | C64: =C58 -> 1238 | D64: 0.1025 | E64: 90 | F64: =C64*(D64*E64/C71) -> 31.289178 | G64: =F64*20% -> 6.2578356 | H64: =F64-G64 -> 25.031342
F65: =F64/C64 -> 0.025273973 | H65: =H64/C64 -> 0.020219178
B66: Annualized Yield | H66: =H65*(365/E64) -> 0.082
B68: Delta (Gross) | C68: =D58-D64 -> 0.003
B69: Delta (Net) | C69: =H60-H66 -> 0.007675
B71: Period (days) | C71: 365
B72: Note: All amounts mentioned in PKR mn unless stated otherwise.

Sheet IOM-009
B4: National Credit Guarantee Company Limited
B5: Investments Team | G5: Date: | H5: =TODAY() -> 46109
B7: Proposed Transaction
B8: Reverse Repo
C9: Placement | D9: Rate | E9: Days | F9: Gross | G9: Tax | H9: Net
B10: Pak Oman Investment Company | C10: 1000 | D10: 0.105 | E10: 30 | F10: =C10*(D10*E10/C23) -> 8.630137 | G10: =F10*20% -> 1.7260274 | H10: =F10-G10 -> 6.9041096
F11: =F10/C10 -> 0.008630137 | H11: =H10/C10 -> 0.0069041096
B12: Annualized Yield | H12: =H11*(365/E10) -> 0.084
B14: Status Quo
C15: Placement | D15: Rate | E15: Days | F15: Gross | G15: Tax | H15: Net
B16: Faysal Bank Limited | C16: 1000 | D16: 0.1025 | E16: 30 | F16: =C16*(D16*E16/C23) -> 8.4246575 | G16: =F16*20% -> 1.6849315 | H16: =F16-G16 -> 6.739726
F17: =F16/C16 -> 0.0084246575 | H17: =H16/C16 -> 0.006739726
B18: Annualized Yield | H18: =H17*(365/E16) -> 0.082
B20: Delta (Gross) | C20: =D10-D16 -> 0.0025
B21: Delta (Net) | C21: =H12-H18 -> 0.002
B23: Period (days) | C23: 365
B24: Note: All amounts mentioned in PKR mn unless stated otherwise.
B52: National Credit Guarantee Company Limited
B53: Investments Team | G53: Date: | H53: =TODAY() -> 46109
B55: Proposed Transaction
B56: Govt. Security Placement
C57: Placement | D57: Rate | E57: Days | F57: Gross | G57: Tax | H57: Net
B58: 6M MTBs | C58: 500 | D58: 0.105 | E58: 180 | F58: =C58*(D58*E58/C71) -> 25.890411 | G58: =F58*15% -> 3.8835616 | H58: =F58-G58 -> 22.006849
F59: =F58/C58 -> 0.051780822 | H59: =H58/C58 -> 0.044013699
B60: Annualized Yield | H60: =H59*(365/E58) -> 0.08925
B62: Status Quo
C63: Placement | D63: Rate | E63: Days | F63: Gross | G63: Tax | H63: Net
B64: Faysal Bank Limited | C64: =C58 -> 500 | D64: 0.1025 | E64: 180 | F64: =C64*(D64*E64/C71) -> 25.273973 | G64: =F64*20% -> 5.0547945 | H64: =F64-G64 -> 20.219178
F65: =F64/C64 -> 0.050547945 | H65: =H64/C64 -> 0.040438356
B66: Annualized Yield | H66: =H65*(365/E64) -> 0.082
B68: Delta (Gross) | C68: =D58-D64 -> 0.0025
B69: Delta (Net) | C69: =H60-H66 -> 0.00725
B71: Period (days) | C71: 365
B72: Note: All amounts mentioned in PKR mn unless stated otherwise.

Sheet IOM-010
B4: National Credit Guarantee Company Limited
B5: Investments Team | G5: Date: | H5: =TODAY() -> 46109
B7: Proposed Transaction
B8: Reverse Repo
C9: Placement | D9: Rate | E9: Days | F9: Gross | G9: Tax | H9: Net
B10: Pak Oman Investment Company | C10: 1000 | D10: 0.105 | E10: 30 | F10: =C10*(D10*E10/C23) -> 8.630137 | G10: =F10*20% -> 1.7260274 | H10: =F10-G10 -> 6.9041096
F11: =F10/C10 -> 0.008630137 | H11: =H10/C10 -> 0.0069041096
B12: Annualized Yield | H12: =H11*(365/E10) -> 0.084
B14: Status Quo
C15: Placement | D15: Rate | E15: Days | F15: Gross | G15: Tax | H15: Net
B16: Faysal Bank Limited | C16: 1000 | D16: 0.1025 | E16: 30 | F16: =C16*(D16*E16/C23) -> 8.4246575 | G16: =F16*20% -> 1.6849315 | H16: =F16-G16 -> 6.739726
F17: =F16/C16 -> 0.0084246575 | H17: =H16/C16 -> 0.006739726
B18: Annualized Yield | H18: =H17*(365/E16) -> 0.082
B20: Delta (Gross) | C20: =D10-D16 -> 0.0025
B21: Delta (Net) | C21: =H12-H18 -> 0.002
B23: Period (days) | C23: 365
B24: Note: All amounts mentioned in PKR mn unless stated otherwise.
B52: National Credit Guarantee Company Limited
B53: Investments Team | G53: Date: | H53: =today() -> 46109
B55: Proposed Transaction
B56: Mutual Fund Placement
C57: Placement | D57: Rate | E57: Days | F57: Gross | G57: Tax | H57: Net
B58: MCB Investment Savings Plan I | C58: =C67 -> 1303 | D58: 0.105 | E58: 30 | F58: =C58*(D58*E58/C72) -> 11.245068 | G58: =F58*25% -> 2.8112671 | H58: =F58-G58 -> 8.4338014
F59: =F58/C58 -> 0.008630137 | H59: =H58/C58 -> 0.0064726027
B60: Annualized Yield (Post Tax) | H60: =H59*(365/E58) -> 0.07875
B62: Status Quo
C63: Placement | D63: Rate | E63: Days | F63: Gross | G63: Tax | H63: Net
B64: Faysal Bank Limited | C64: 170 | D64: 0.1025 | E64: 30 | F64: =C64*(D64*E64/C72) -> 1.4321918 | G64: =F64*29% -> 0.41533562 | H64: =F64-G64 -> 1.0168562
B65: Alfalah Govt. Securities Fund | C65: 823 | D65: 0.0887 | E65: 30 | F65: =C65*(D65*E65/C72) -> 6.0000082 | G65: =F65*25% -> 1.5000021 | H65: =F65-G65 -> 4.5000062
B66: Alfalah MTS Fund | C66: 310 | D66: 0.092 | E66: 30 | F66: =C66*(D66*E66/C72) -> 2.3441096 | G66: =F66*25% -> 0.5860274 | H66: =F66-G66 -> 1.7580822
C67: =C64+C65+C66 -> 1303 | H67: =(H64+H65+H66)/C67 -> 0.0055832268
B68: Annualized Yield (Post Tax) | H68: =H67*(365/E66) -> 0.067929259
B70: Delta (Net) | C70: =D58-D64 -> 0.0025
B71: Delta (Net) - Annualized | C71: =H60-H68 -> 0.010820741
B72: Period (days) | C72: 365
B73: Note: All amounts mentioned in PKR mn unless stated otherwise.

Sheet Strategy Post Allocation
G2: Date | H2: =Today() -> 46109
B3: Post Allocation
B4: Instrument | C4: Exisiting Placement (PKR) | D4: Date of Placement | E4: Date of Maturity | F4: Rate | G4: Days to Maturity | H4: Remaining Days | I4: Concentration (%)
B5: MTBs (1Y) | C5: 2000000000 | D5: 45895 | E5: 46240 | F5: 0.1088 | G5: =E5-D5 -> 345 | H5: =E5-$H$2 -> 131 | I5: =C5/$C$19 -> 0.21634585
B6: MTBs (6M) | C6: 500000000 | D6: 46002 | E6: 46184 | F6: 0.1092 | G6: =E6-D6 -> 182 | H6: =E6-$H$2 -> 75 | I6: =C6/$C$19 -> 0.054086462
B7: MTBs (1Y) | C7: 1200000000 | D7: 46072 | E7: =D7+364 -> 46436 | F7: 0.1055 | G7: =E7-D7 -> 364 | H7: =E7-$H$2 -> 327 | I7: =C7/$C$19 -> 0.12980751
B8: Faysal Bank | C8: 261777528 | F8: 0.1025 | G8: 1 | H8: 1 | I8: =C8/$C$19 -> 0.02831724
B9: COI | C9: 1300000000 | D9: 46082 | E9: 46112 | F9: 0.1005 | G9: 30 | H9: =E9-H2 -> 3 | I9: =C9/$C$19 -> 0.1406248
B10: Alfalah Government Securities Fund Plan II* | C10: 816606719 | F10: 0.1 | G10: =0.78*365 -> 284.7 | H10: =1*G10 -> 284.7 | I10: =C10/$C$19 -> 0.088334736 | L10: 100 | N10: 0.15
B11: Alfalah MTS Fund (Formerly: Faysal MTS Fund)* | C11: 303753987 | F11: 0.102 | G11: 1 | H11: =1*G11 -> 1 | I11: =C11/$C$19 -> 0.032857957 | L11: 0.1025 | M11: =$L$10*(L11*(90/365)) -> 2.5273973 | N11: =M11*$N$10 -> 0.37910959 | O11: =M11-N11 -> 2.1482877 | P11: =M11+L10 -> 102.5274 | R11: 0.15
B12: Alfalah Income Multiplier* | C12: 500000000 | F12: 0.102 | G12: =0.22*365 -> 80.3 | H12: =1*G12 -> 80.3 | I12: =C12/$C$19 -> 0.054086462 | L12: 0.105 | M12: =P11*(L12*(90/365)) -> 2.6544765 | N12: =M12*$N$10 -> 0.39817147 | O12: =M12-N12 -> 2.256305 | P12: =P11+M12 -> 105.18187 | Q12: =P11*L11*(90/365) -> 2.5912746
B13: MCB Investment Saving Plan I* | C13: 800000000 | F13: 0.1 | G13: 1 | H13: =1*G13 -> 1 | I13: =C13/$C$19 -> 0.086538339 | L13: 0.1075 | M13: =P12*(L13*(90/365)) -> 2.7880401 | N13: =M13*$N$10 -> 0.41820601 | O13: =M13-N13 -> 2.3698341 | P13: =P12+M13 -> 107.96991
B14: Daewoo Short Term SUKUK | C14: 275000000 | D14: 45713 | E14: =D14+180 -> 45893 | F14: 0.1309 | G14: =E14-D14 -> 180 | H14: =E14-$H$2 -> -216 | I14: =C14/$C$19 -> 0.029747554 | L14: 0.11 | M14: =P13*(L14*(90/365)) -> 2.928499 | N14: =M14*$N$10 -> 0.43927485 | O14: =M14-N14 -> 2.4892242 | P14: =P13+M14 -> 110.89841
B15: Reallocation | M15: =SUM(M11:M14) -> 10.898413 | N15: =M15*N14 -> 4.7873987 | O15: =M15-N15 -> 6.1110141 | P15: =P14+L14 -> 111.00841
B16: MTBs (1Y) * | C16: 384022350 | D16: 46086 | E16: =D16+364 -> 46450 | F16: 0.107 | G16: =E16-D16 -> 364 | H16: =E16-D16 -> 364 | I16: =C16/$C$19 -> 0.04154082 | P16: =P15/L10 -> 1.1100841
B17: MTBs (1Y) * | C17: 451587500 | D17: 46086 | E17: =D17+364 -> 46450 | F17: 0.1072 | G17: =E17-D17 -> 364 | H17: =E17-D17 -> 364 | I17: =C17/$C$19 -> 0.04884954
B18: MTBs (1Y) * | C18: 451709500 | D18: 46086 | E18: =D18+364 -> 46450 | F18: =10.75% -> 0.1075 | G18: =E18-D18 -> 364 | H18: =E18-D18 -> 364 | I18: =C18/$C$19 -> 0.048862737 | P18: =P16-1 -> 0.11008413
B19: Total | C19: =SUM(C5:C14)+C16+C17+C18 -> 9244457584 | F19: =sumproduct(F5:F18,I5:I18) -> 0.10535855 | G19: =sumproduct(G5:G18,I5:I18) -> 221.63417 | H19: =sumproduct(H5:H18,I5:I18) -> 149.16913 | I19: =SUM(I5:I18) -> 1
B20: *Expected Rate on the Treasury Bills based on Auction
B21: Pre Allocation
B22: Instrument | C22: Exisiting Placement (PKR) | D22: Date of Placement | E22: Date of Maturity | F22: Rate | G22: Days to Maturity | H22: Remaining Days | I22: Concentration (%)
B23: MTBs (1Y) | C23: 2000000000 | D23: 45895 | E23: 46240 | F23: 0.1088 | G23: =E23-D23 -> 345 | H23: =E23-$H$2 -> 131 | I23: =C23/$C$19 -> 0.21634585
B24: MTBs (3M) | C24: 500000000 | D24: 46002 | E24: 46086 | F24: 0.1092 | G24: =E24-D24 -> 84 | H24: =E24-$H$2 -> -23 | I24: =C24/$C$19 -> 0.054086462
B25: MTBs (6M) | C25: 500000000 | D25: 46002 | E25: 46184 | F25: 0.1092 | G25: =E25-D25 -> 182 | H25: =E25-$H$2 -> 75 | I25: =C25/$C$19 -> 0.054086462
B26: Faysal Bank | C26: =2500000000+24096878 -> 2524096878 | F26: 0.1025 | G26: 1 | H26: 1 | I26: =C26/$C$19 -> 0.27303894
B27: COI | C27: 1300000000 | D27: 46051 | E27: 46081 | F27: 0.1005 | G27: 30 | H27: =E27-$H$2 -> -28 | I27: =C27/$C$19 -> 0.1406248
B28: Alfalah Government Securities Fund Plan II* | C28: 816606719 | F28: 0.1 | G28: 1 | H28: 1 | I28: =C28/$C$19 -> 0.088334736
B29: Alfalah MTS Fund (Formerly: Faysal MTS Fund)* | C29: 303753987 | F29: 0.1015 | G29: 1 | H29: 1 | I29: =C29/$C$19 -> 0.032857957
B30: Alfalah Income Multiplier* | C30: 500000000 | F30: 0.102 | G30: 1 | H30: 1 | I30: =C30/$C$19 -> 0.054086462
B31: MCB Investment Saving Plan I* | C31: 800000000 | F31: 0.1 | G31: 1 | H31: 1 | I31: =C31/$C$19 -> 0.086538339
B32: Total | C32: =sum(C23:C31) -> 9244457584 | F32: =sumproduct(F23:F31,I23:I31) -> 0.1038094 | G32: =sumproduct(G23:G31,I23:I31) -> 93.779916 | H32: =sumproduct(H23:H31,I23:I31) -> 27.751164 | I32: =sum(I23:I31) -> 1

Sheet PKRV Rates
A1: Tenor | B1: 46100 | C1: 46105 | D1: 46106 | E1: 46107 | F1: 46108
A2: 1W | B2: 10.5 | C2: 10.49 | D2: 10.48 | E2: 10.5 | F2: 10.51
A3: 2W | B3: 10.58 | C3: 10.56 | D3: 10.56 | E3: 10.57 | F3: 10.61
A4: 1M | B4: 10.85 | C4: 10.82 | D4: 10.77 | E4: 10.77 | F4: 10.87
A5: 2M | B5: 11.03 | C5: 11.03 | D5: 11.01 | E5: 11.03 | F5: 11.08
A6: 3M | B6: 11.16 | C6: 11.16 | D6: 11.16 | E6: 11.18 | F6: 11.24
A7: 4M | B7: 11.28 | C7: 11.28 | D7: 11.28 | E7: 11.32 | F7: 11.41
A8: 6M | B8: 11.36 | C8: 11.34 | D8: 11.34 | E8: 11.44 | F8: 11.56
A9: 9M | B9: 11.67 | C9: 11.68 | D9: 11.69 | E9: 11.72 | F9: 11.9
A10: 1Y | B10: 11.63 | C10: 11.65 | D10: 11.66 | E10: 11.72 | F10: 11.88
A11: 2Y | B11: 11.58 | C11: 11.57 | D11: 11.57 | E11: 11.68 | F11: 12.37
A12: 3Y | B12: 11.55 | C12: 11.54 | D12: 11.53 | E12: 11.61 | F12: 12.4
... A21: 20Y | B21: 12.73 | C21: 12.76 | D21: 12.77 | E21: 12.88 | F21: 12.83

Sheet Log
A1: Timestamp | B1: Date | C1: Status
A2: 46108.524 | B2: 46108 | C2: No file found
A3: 46108.524 | B3: 46107 | C3: OK: PKRV2603202624816.csv (20 tenors)
A4: 46108.752 | B4: 46108 | C4: OK: PKRV2703202624821.csv (20 tenors)
A5: 46108.752 | B5: 46107 | C5: OK: PKRV2603202624816.csv (20 tenors)
A6: 46109.752 | B6: 46108 | C6: OK: PKRV2703202624821.csv (20 tenors)
A7: 46109.752 | B7: 46107 | C7: OK: PKRV2603202624816.csv (20 tenors)
A8: 46109.866 | B8: 46108 | C8: OK: PKRV2703202624821.csv (20 tenors)
A9: 46109.866 | B9: 46107 | C9: OK: PKRV2603202624816.csv (20 tenors)
A10: 46109.868 | B10: 46107 | C10: OK: PKRV2703202624821.csv (20 tenors)
A11: 46109.869 | B11: 46106 | C11: OK: PKRV2603202624816.csv (20 tenors)
A12: 46109.87 | B12: 46107 | C12: OK: PKRV2703202624821.csv (20 tenors)
A13: 46109.87 | B13: 46105 | C13: OK: PKRV2503202624809.csv (20 tenors)
... A71: 46109.894 | B71: 46108 | C71: OK: PKRV2703202624821.csv (20 tenors)

Sheet Config
A1: Key | B1: Value
A2: LAST_SERIAL | B2: 24821

Sheet MUFAP Data
A1: Sector | B1: Category | C1: Fund Name | D1: Rating | E1: NAV | F1: YTD | G1: MTD | H1: 1 Day | I1: 15 Days | J1: 30 Days | K1: 90 Days | L1: 180 Days | M1: 270 Days | N1: 365 Days | O1: 2 Years | P1: 3 Years | Q1: Date Fetched
A2: Open-End Funds | B2: Money Market (Annualized Return ) | C2: ABL Cash Fund | D2: AA+(f) | E2: N/A | F2: 46111 | G2: 11.0216 | H2: 10.03 | I2: 9.31 | J2: 9.93 | K2: 9.51 | L2: 9.31 | M2: 9.43 | N2: 9.93 | O2: 10.04 | P2: 10.56 | Q2: 15.04
A3: Open-End Funds | B3: Money Market (Annualized Return ) | C3: ABL Money Market Plan I | D3: AA+(f) | E3: N/A | F3: 46111 | G3: 10.7282 | H3: 9.53 | I3: 8.46 | J3: 8.83 | K3: 8.6 | L3: 8.49 | M3: 8.47 | N3: 9.27 | O3: 9.46 | P3: 10.11 | Q3: 14.61
A4: Open-End Funds | B4: Money Market (Annualized Return ) | C4: AKD Cash Fund | D4: AA+(f) | E4: N/A | F4: 46108 | G4: 55.8398 | H4: 10.01 | I4: 8.63 | J4: 6.79 | K4: 8.77 | L4: 8.79 | M4: 9.41 | N4: 10.06 | O4: 10.01 | P4: 10.36 | Q4: 14.86
A5: Open-End Funds | B5: Money Market (Annualized Return ) | C5: AL Habib Cash Fund | D5: AAA(f) | E5: N/A | F5: 46108 | G5: 109.1993 | H5: 10.15 | I5: 9.15 | J5: 7.92 | K5: 8.67 | L5: 9.16 | M5: 9.39 | N5: 9.95 | O5: 10.16 | P5: 10.55 | Q5: 14.83
A6: Open-End Funds | B6: Money Market (Annualized Return ) | C6: AL Habib Money Market Fund | D6: AAA(f) | E6: N/A | F6: 46108 | G6: 107.9552 | H6: 10.11 | I6: 9.12 | J6: 7.92 | K6: 8.62 | L6: 9.17 | M6: 9.39 | N6: 9.94 | O6: 10.11 | P6: 10.46 | Q6: 14.74
A7: Open-End Funds | B7: Money Market (Annualized Return ) | C7: Alfalah Cash Fund - II | D7: AA+(f) | E7: N/A | F7: 46109 | G7: 110.1617 | H7: 9.95 | I7: 9.74 | J7: 9.89 | K7: 9.91 | L7: 9.76 | M7: 9.95 | N7: 10.02 | O7: 9.95 | P7: 10.58 | Q7: 15.68
A8: Open-End Funds | B8: Money Market (Annualized Return ) | C8: Alfalah GHP Cash Fund | D8: AA+(f) | E8: Nil | F8: 46109 | G8: 539.7433 | H8: 9.41 | I8: 8.65 | J8: 8.32 | K8: 8.88 | L8: 8.66 | M8: 8.66 | N8: 9.12 | O8: 9.41 | P8: 9.87 | Q8: 14.31
A9: Open-End Funds | B9: Money Market (Annualized Return ) | C9: Alfalah GHP Money Market Fund | D9: AA+(f) | E9: N/A | F9: 46108 | G9: 106.3205 | H9: 9.97 | I9: 9.32 | J9: 9.2 | K9: 9.51 | L9: 9.3 | M9: 9.45 | N9: 9.85 | O9: 9.97 | P9: 10.41 | Q9: 14.92
A10: Open-End Funds | B10: Money Market (Annualized Return ) | C10: Alfalah Money Market Fund - II | D10: AA(f) | E10: N/A | F10: 46109 | G10: 111.151 | H10: 10.15 | I10: 9.88 | J10: 9.75 | K10: 9.77 | L10: 9.89 | M10: 10.93 | N10: 10.07 | O10: 10.15 | P10: 10.64 | Q10: 14.67
A11: Open-End Funds | B11: Money Market (Annualized Return ) | C11: Askari Cash Fund | D11: AA+(f) | E11: N/A | F11: 46109 | G11: 110.6747 | H11: 9.1 | I11: 8.9 | J11: 8.1 | K11: 9.12 | L11: 8.89 | M11: 8.69 | N11: 8.77 | O11: 9.1 | P11: 9.53 | Q11: 14
A12: Open-End Funds | B12: Money Market (Annualized Return ) | C12: Atlas Liquid Fund | D12: AA+(f) | E12: N/A | F12: 46109 | G12: 539.7838 | H12: 10.31 | I12: 9.13 | J12: 9.31 | K12: 9.32 | L12: 9.21 | M12: 9.5 | N12: 10.17 | O12: 10.31 | P12: 10.64 | Q12: 15.22
A13: Open-End Funds | B13: Money Market (Annualized Return ) | C13: Atlas Money Market Fund | D13: AA+(f) | E13: N/A | F13: 46108 | G13: 552.0045 | H13: 10.4 | I13: 9.18 | J13: 8.69 | K13: 9.32 | L13: 9.26 | M13: 9.53 | N13: 10.18 | O13: 10.4 | P13: 10.73 | Q13: 15.28
... A19: Open-End Funds | B19: Money Market (Annualized Return ) | C19: MCB Cash Management Optimizer | D19: AA+(f) | E19: N/A | F19: 46111 | G19: 109.8664 | H19: 9.88 | I19: 8.89 | J19: 9.09 | K19: 8.91 | L19: 8.9 | M19: 9.27 | N19: 9.73 | O19: 9.87 | P19: 10.28 | Q19: 14.93
A20: Open-End Funds | B20: Money Market (Annualized Return ) | C20: NBP Cash Plan I | E20: N/A | F20: 46108 | G20: 10.8023 | H20: 9.62 | I20: 8.61 | J20: 8.43 | K20: 8.7 | L20: 8.66 | M20: 8.98 | N20: 9.45 | O20: 9.62 | P20: 10.07 | Q20: 14.7
A21: Open-End Funds | B21: Money Market (Annualized Return ) | C21: NBP Cash Plan II | E21: N/A | F21: 46108 | G21: 10 | H21: 9.78 | I21: 8.68 | J21: 8.4 | K21: 8.8 | L21: 8.72 | M21: 9.09 | N21: 9.63 | O21: 9.78 | P21: 10.24 | Q21: 14.93
A22: Open-End Funds | B22: Money Market (Annualized Return ) | C22: NBP Government Securities Liquid Fund | D22: AAA(f) | E22: N/A | F22: 46108 | G22: 11.0338 | H22: 9.5 | I22: 7.99 | J22: 7.59 | K22: 8.37 | L22: 8.05 | M22: 8.48 | N22: 9.24 | O22: 9.5 | P22: 10.1 | Q22: 14.81
A23: Open-End Funds | B23: Money Market (Annualized Return ) | C23: NBP Money Market Fund | D23: AA(f) | E23: N/A | F23: 46108 | G23: 10.7691 | H23: 9.92 | I23: 8.86 | J23: 8.47 | K23: 8.96 | L23: 8.9 | M23: 9.24 | N23: 9.77 | O23: 9.92 | P23: 10.37 | Q23: 14.97
A24: Open-End Funds | B24: Money Market (Annualized Return ) | C24: NIT Money Market Fund | D24: AAA(f) | E24: N/A | F24: 46111 | G24: 10.5113 | H24: 10.29 | I24: 9.24 | J24: 10.07 | K24: 9.41 | L24: 9.25 | M24: 9.51 | N24: 10.16 | O24: 10.28 | P24: 10.72 | Q24: 15.38
A25: Open-End Funds | B25: Money Market (Annualized Return ) | C25: Pakistan Cash Management Fund | D25: AA+(f) | E25: N/A | F25: 46108 | G25: 50.4678 | H25: 9.8 | I25: 8.08 | J25: N/A | K25: 7.52 | L25: 8.26 | M25: 9.29 | N25: 9.69 | O25: 9.78 | P25: 9.98 | Q25: 14.67
A26: Open-End Funds | B26: Money Market (Annualized Return ) | C26: UBL Cash Fund | D26: AA+(f) | E26: N/A | F26: 46111 | G26: 107.6025 | H26: 9.65 | I26: 9.26 | J26: 10.66 | K26: 9.45 | L26: 9.3 | M26: 8.99 | N26: 9.41 | O26: 9.64 | P26: 10.06 | Q26: 14.62
A27: Open-End Funds | B27: Money Market (Annualized Return ) | C27: UBL Liquidity Fund | E27: N/A | F27: 46108 | G27: 105.6822 | H27: 10.44 | I27: 9.83 | J27: 9.82 | K27: 9.89 | L27: 9.86 | M27: 9.98 | N27: 10.32 | O27: N/A | P27: N/A | Q27: N/A
A28: Open-End Funds | B28: Money Market (Annualized Return ) | C28: UBL Liquidity Plus Fund | D28: AA+(f) | E28: N/A | F28: 46111 | G28: 108.8185 | H28: 9.67 | I28: 7.55 | J28: 8.94 | K28: 7.67 | L28: 7.61 | M28: 8.38 | N28: 9.31 | O28: 9.67 | P28: 10.04 | Q28: 14.62
A29: Open-End Funds | B29: Money Market (Annualized Return ) | C29: UBL Money Market Fund | D29: AA+(f) | E29: N/A | F29: 46111 | G29: 108.613 | H29: 9.88 | I29: 8.88 | J29: 9.45 | K29: 9 | L29: 8.89 | M29: 9.12 | N29: 9.65 | O29: 9.88 | P29: 10.24 | Q29: 14.74
A30: Open-End Funds | B30: Income (Annualized Return ) | C30: ABL Financial Sector Fund Plan I | D30: A+(f) | E30: N/A | F30: 46110 | G30: 10.7755 | H30: 10.25 | I30: 8.95 | J30: 10.51 | K30: 8.95 | L30: 8.96 | M30: 9.51 | N30: 10.16 | O30: 10.24 | P30: 10.53 | Q30: 15.11
A31: Open-End Funds | B31: Income (Annualized Return ) | C31: ABL Government Securities Fund | D31: AA-(f) | E31: N/A | F31: 46108 | G31: 10.8858 | H31: 9.56 | I31: 4.9 | J31: -15.07 | K31: 5.69 | L31: 5.33 | M31: 7.87 | N31: 9.21 | O31: 9.56 | P31: 10.56 | Q31: 16.18
A32: Open-End Funds | B32: Income (Annualized Return ) | C32: ABL Income Fund | D32: A+(f) | E32: N/A | F32: 46108 | G32: 10.9298 | H32: 9.7 | I32: 5.48 | J32: -7.34 | K32: 6.07 | L32: 6.01 | M32: 8.92 | N32: 9.32 | O32: 9.7 | P32: 10.9 | Q32: 16.11
A33: Open-End Funds | B33: Income (Annualized Return ) | C33: AL Habib Government Securities Fund | D33: AAA(f) | E33: N/A | F33: 46107 | G33: 107.776 | H33: 9.86 | I33: 6.51 | J33: 6.13 | K33: 6.08 | L33: 7.03 | M33: 8.52 | N33: 9.6 | O33: 9.95 | P33: 10.72 | Q33: 15.33
A34: Open-End Funds | B34: Income (Annualized Return ) | C34: AL Habib Income Fund | D34: AA(f) | E34: N/A | F34: 46107 | G34: 109.7125 | H34: 9.9 | I34: 6.32 | J34: 3.03 | K34: 6.56 | L34: 6.88 | M34: 8.33 | N34: 9.69 | O34: 9.91 | P34: 10.44 | Q34: 15.19
A35: Open-End Funds | B35: Income (Annualized Return ) | C35: AL Habib Sovereign Income Fund Plan 1 | E35: N/A | F35: 46107 | G35: 107.9819 | H35: 10.83 | I35: 10.76 | J35: 10.44 | K35: 11.17 | L35: 10.73 | M35: 10.45 | N35: 10.97 | O35: 10.83 | P35: N/A | Q35: N/A
A36: Open-End Funds | B36: Income (Annualized Return ) | C36: AL Habib Sovereign Income Fund Plan 2 | E36: N/A | F36: 46107 | G36: 107.9755 | H36: 10.82 | I36: 10.27 | J36: 10.51 | K36: 10.74 | L36: 10.23 | M36: 10.11 | N36: 10.67 | O36: 10.83 | P36: N/A | Q36: N/A
A37: Open-End Funds | B37: Income (Annualized Return ) | C37: AL Habib Sovereign Income Fund Plan 3 | E37: N/A | F37: 46107 | G37: 107.9829 | H37: 10.83 | I37: 10.19 | J37: 10.22 | K37: 10.34 | L37: 10.18 | M37: 9.98 | N37: 10.66 | O37: 10.84 | P37: N/A | Q37: N/A
A38: Open-End Funds | B38: Income (Annualized Return ) | C38: Alfalah Financial Sector Income Fund | D38: A+(f) | E38: N/A | F38: 46108 | G38: 107.916 | H38: 10.21 | I38: 8.53 | J38: 3.61 | K38: 8.47 | L38: 8.67 | M38: 9.12 | N38: 10.05 | O38: 10.21 | P38: 10.65 | Q38: 3.88
A39: Open-End Funds | B39: Income (Annualized Return ) | C39: Alfalah Financial Sector Opportunity Fund | D39: A+(f) | E39: N/A | F39: 46108 | G39: 125.6107 | H39: 13.04 | I39: 10.25 | J39: 10.22 | K39: 10.4 | L39: 10.23 | M39: 12.6 | N39: 11.86 | O39: 13.04 | P39: 12.68 | Q39: 14.82
A40: Open-End Funds | B40: Income (Annualized Return ) | C40: Alfalah GHP Income Fund | D40: AA-(f) | E40: 12 | F40: 46108 | G40: 122.5677 | H40: 9.75 | I40: 4.06 | J40: -13.61 | K40: 5.01 | L40: 3.82 | M40: 8.35 | N40: 9.91 | O40: 9.75 | P40: 10.42 | Q40: 15.71
A41: Open-End Funds | B41: Income (Annualized Return ) | C41: Alfalah GHP Sovereign Fund | D41: AA-(f) | E41: N/A | F41: 46108 | G41: 113.8119 | H41: 7.59 | I41: -12.55 | J41: -68.91 | K41: -10.27 | L41: -10.39 | M41: 1.97 | N41: 6.67 | O41: 7.59 | P41: 10.11 | Q41: 15.41
A42: Open-End Funds | B42: Income (Annualized Return ) | C42: Alfalah Government Securities Fund - II | D42: AA(f) | E42: N/A | F42: 46108 | G42: 133.726 | H42: 8.11 | I42: -7.11 | J42: -63.73 | K42: -4.07 | L42: -5.51 | M42: 3.03 | N42: 7.82 | O42: 8.11 | P42: 10.56 | Q42: 15.65
A43: Open-End Funds | B43: Income (Annualized Return ) | C43: Alfalah Government Securities Fund Plan I | E43: N/A | F43: 46108 | G43: 105.0932 | H43: 6.55 | I43: -27.38 | J43: -215.68 | K43: -25.51 | L43: -23.77 | M43: -3.24 | N43: 5.61 | O43: 6.55 | P43: 9.47 | Q43: N/A
A44: Open-End Funds | B44: Income (Annualized Return ) | C44: Alfalah Government Securities Fund Plan II | E44: N/A | F44: 46108 | G44: 105.8694 | H44: 7.81 | I44: -1.93 | J44: -27.78 | K44: 2.3 | L44: -0.9 | M44: 4.24 | N44: 7.43 | O44: 7.81 | P44: 10.18 | Q44: N/A
A45: Open-End Funds | B45: Income (Annualized Return ) | C45: Alfalah MTS Fund | D45: AA-(f) | E45: N/A | F45: 46108 | G45: 112.2606 | H45: 11.24 | I45: 9.49 | J45: 8.76 | K45: 9.45 | L45: 9.65 | M45: 10.21 | N45: 10.87 | O45: 11.24 | P45: 11.63 | Q45: 14.23
A46: Open-End Funds | B46: Income (Annualized Return ) | C46: Alfalah Savings Growth Fund | D46: AA-(f) | E46: N/A | F46: 46108 | G46: 111.1438 | H46: 8.8 | I46: -13.05 | J46: -117.24 | K46: -12.63 | L46: -10.73 | M46: 2.15 | N46: 8.07 | O46: 8.8 | P46: 10.33 | Q46: 17.9
A47: Open-End Funds | B47: Income (Annualized Return ) | C47: Askari Sovereign Yield Enhancer | D47: AA-(f) | E47: N/A | F47: 46108 | G47: 111.3504 | H47: 9.14 | I47: 8.62 | J47: 8.69 | K47: 8.54 | L47: 8.68 | M47: 8.58 | N47: 8.97 | O47: 9.14 | P47: 9.85 | Q47: 14.45
A48: Open-End Funds | B48: Income (Annualized Return ) | C48: Atlas Income Fund | D48: AA-(f) | E48: N/A | F48: 46108 | G48: 567.5611 | H48: 9.78 | I48: 3.95 | J48: -7.99 | K48: 5.73 | L48: 4.56 | M48: 7.41 | N48: 9.34 | O48: 9.78 | P48: 10.79 | Q48: 15.75
A49: Open-End Funds | B49: Income (Annualized Return ) | C49: Atlas Sovereign Fund | D49: AA-(f) | E49: N/A | F49: 46108 | G49: 109.672 | H49: 9.18 | I49: -1.92 | J49: -34.6 | K49: 2.42 | L49: -0.73 | M49: 5.43 | N49: 8.67 | O49: 9.18 | P49: 10.07 | Q49: 16.54
A50: Open-End Funds | B50: Income (Annualized Return ) | C50: AWT Financial Sector Income Fund | D50: A+(f) | E50: N/A | F50: 46108 | G50: 105.5794 | H50: 7.06 | I50: 5.34 | J50: 4.93 | K50: 4.66 | L50: 5.48 | M50: 6.28 | N50: 6.74 | O50: 7.06 | P50: 7.64 | Q50: 12.8
A51: Open-End Funds | B51: Income (Annualized Return ) | C51: AWT Income Fund | D51: A+(f) | E51: N/A | F51: 46108 | G51: 116.7417 | H51: 7.4 | I51: -7.49 | J51: -20.73 | K51: -15.03 | L51: -6.5 | M51: 2.61 | N51: 6.17 | O51: 7.4 | P51: 8.4 | Q51: 14.54
A52: Open-End Funds | B52: Income (Annualized Return ) | C52: HBL Financial Sector Income Fund Plan I | E52: N/A | F52: 46106 | G52: 109.4986 | H52: 9.39 | I52: 6.8 | J52: 8.36 | K52: 7.03 | L52: 7.07 | M52: 8.21 | N52: 9.12 | O52: 9.72 | P52: 10.29 | Q52: 14.92
A53: Open-End Funds | B53: Income (Annualized Return ) | C53: HBL Financial Sector Income Fund Plan II | E53: N/A | F53: 46108 | G53: 101.6918 | H53: 16.19 | I53: 10.23 | J53: 10.15 | K53: 10.21 | L53: 10.23 | M53: 10.83 | N53: 11.1 | O53: 11.54 | P53: 11.63 | Q53: 16.18
A54: Open-End Funds | B54: Income (Annualized Return ) | C54: HBL Government Securities Fund | D54: AA-(f) | E54: N/A | F54: 46108 | G54: 122.2379 | H54: 9.69 | I54: -6.12 | J54: -45.95 | K54: -2.74 | L54: -4.57 | M54: 4.97 | N54: 9.65 | O54: 9.69 | P54: 10.54 | Q54: 16.56
A55: Open-End Funds | B55: Income (Annualized Return ) | C55: HBL Income Fund | D55: A+(f) | E55: N/A | F55: 46105 | G55: 121.2221 | H55: 9.59 | I55: -0.47 | J55: 11.13 | K55: 6.38 | L55: 1.11 | M55: 6.51 | N55: 9.61 | O55: 9.25 | P55: 9.82 | Q55: 14.92
A56: Open-End Funds | B56: Income (Annualized Return ) | C56: JS Government Securities Fund | D56: AA(f) | E56: N/A | F56: 46108 | G56: 117.6845 | H56: 6.75 | I56: -15.72 | J56: -191.7 | K56: -16.16 | L56: -13.3 | M56: -0.32 | N56: 5.59 | O56: 6.75 | P56: 8.7 | Q56: 14.2
A57: Open-End Funds | B57: Income (Annualized Return ) | C57: JS Income Fund | D57: A+(f) | E57: N/A | F57: 46108 | G57: 123.2696 | H57: 7.86 | I57: 0.09 | J57: -27.41 | K57: 0.66 | L57: 1 | M57: 4.28 | N57: 6.33 | O57: 7.86 | P57: 9.26 | Q57: 13.9
A58: Open-End Funds | B58: Income (Annualized Return ) | C58: JS Microfinance Sector Fund | D58: A(f) | E58: N/A | F58: 46108 | G58: 117.2817 | H58: 11.4 | I58: 10.67 | J58: 10.69 | K58: 10.77 | L58: 10.69 | M58: 10.91 | N58: 11.28 | O58: 11.4 | P58: 11.51 | Q58: 16.04
A59: Open-End Funds | B59: Income (Annualized Return ) | C59: Lakson Income Fund | D59: A+(f) | E59: N/A | F59: 46106 | G59: 109.5542 | H59: 9.75 | I59: -4.36 | J59: 7.85 | K59: -1.89 | L59: -2.69 | M59: 5.24 | N59: 8.95 | O59: 9.74 | P59: 11.44 | Q59: 16.77
A60: Open-End Funds | B60: Income (Annualized Return ) | C60: MCB DCF Income Fund | D60: AA-(f) | E60: N/A | F60: 46108 | G60: 116.6317 | H60: 8.76 | I60: 2.22 | J60: -9.53 | K60: 2.51 | L60: 2.72 | M60: 6.47 | N60: 8.19 | O60: 8.76 | P60: 9.68 | Q60: 14.95
A61: Open-End Funds | B61: Income (Annualized Return ) | C61: MCB Government Securities Plan I | D61: AA(f) | E61: N/A | F61: 46108 | G61: 107.0949 | H61: 9.07 | I61: -1.07 | J61: -27.41 | K61: -3.29 | L61: 0.05 | M61: 5.62 | N61: 8.32 | O61: 9.07 | P61: 10.37 | Q61: N/A
A62: Open-End Funds | B62: Income (Annualized Return ) | C62: MCB Pakistan Sovereign Fund | D62: AA-(f) | E62: N/A | F62: 46108 | G62: 58.19 | H62: 7.76 | I62: -10.15 | J62: -100.08 | K62: -8.75 | L62: -8.31 | M62: 1.82 | N62: 6.77 | O62: 7.76 | P62: 9.87 | Q62: 15.67
A63: Open-End Funds | B63: Income (Annualized Return ) | C63: NBP Financial Sector Income Fund | D63: A+(f) | E63: N/A | F63: 46108 | G63: 11.4935 | H63: 10.31 | I63: 8.46 | J63: 5.73 | K63: 8.26 | L63: 8.59 | M63: 9.55 | N63: 10.26 | O63: 10.31 | P63: 10.74 | Q63: 15.2
A64: Open-End Funds | B64: Income (Annualized Return ) | C64: NBP Government Securities Plan IV | D64: AA(f) | E64: N/A | F64: 46108 | G64: 10.7399 | H64: 8.97 | I64: -2.66 | J64: -63.11 | K64: -1.97 | L64: -1.49 | M64: 5.16 | N64: 8.7 | O64: 8.97 | P64: 10.26 | Q64: 15.94
A65: Open-End Funds | B65: Income (Annualized Return ) | C65: NBP Government Securities Plan VIII | E65: N/A | F65: 46108 | G65: 10.6066 | H65: 10.35 | I65: 5.26 | J65: 15.15 | K65: 4.04 | L65: 5.51 | M65: 8.68 | N65: 10.36 | O65: N/A | P65: N/A | Q65: N/A
A66: Open-End Funds | B66: Income (Annualized Return ) | C66: NBP Government Securities Savings Fund | D66: AA-(f) | E66: N/A | F66: 46108 | G66: 11.2122 | H66: 8.76 | I66: -6.1 | J66: -60.44 | K66: -5.41 | L66: -4.62 | M66: 4.06 | N66: 8.3 | O66: 8.76 | P66: 10.27 | Q66: 15.73
A67: Open-End Funds | B67: Income (Annualized Return ) | C67: NBP Income Opportunity Fund | D67: A+(f) | E67: N/A | F67: 46108 | G67: 12.0469 | H67: 14.18 | I67: 6.99 | J67: 1.83 | K67: 7.39 | L67: 6.9 | M67: 8.89 | N67: 9.98 | O67: 14.18 | P67: 15.5 | Q67: 18.65
A68: Open-End Funds | B68: Income (Annualized Return ) | C68: NBP Income Plan I | E68: N/A | F68: 46108 | G68: 10.1169 | H68: 10.08 | I68: 8.3 | J68: 5.77 | K68: 8.11 | L68: 8.42 | M68: 9.42 | N68: 10.12 | O68: 10.08 | P68: 10.46 | Q68: 15.02
A69: Open-End Funds | B69: Income (Annualized Return ) | C69: NBP Mahana Amdani Fund | D69: AA-(f) | E69: N/A | F69: 46108 | G69: 11.1056 | H69: 10.61 | I69: 9.8 | J69: 9.86 | K69: 9.79 | L69: 9.81 | M69: 10.19 | N69: 10.56 | O69: 10.61 | P69: 10.87 | Q69: 15.11
A70: Open-End Funds | B70: Income (Annualized Return ) | C70: NBP Savings Fund | D70: A+(f) | E70: N/A | F70: 46109 | G70: 10.9346 | H70: 13.87 | I70: 8.86 | J70: 8.69 | K70: 8.98 | L70: 8.91 | M70: 9.35 | N70: 9.87 | O70: 13.87 | P70: 13.38 | Q70: 16.84
A71: Open-End Funds | B71: Income (Annualized Return ) | C71: NIT - Government Bond Fund | D71: AA(f) | E71: N/A | F71: 46108 | G71: 10.6443 | H71: 7.7 | I71: -6.7 | J71: -57.85 | K71: -6 | L71: -5.01 | M71: 2.93 | N71: 6.6 | O71: 7.7 | P71: 9.31 | Q71: 14.99
A72: Open-End Funds | B72: Income (Annualized Return ) | C72: NIT - Income Fund | D72: AA-(f) | E72: N/A | F72: 46108 | G72: 11.0401 | H72: 9.67 | I72: 4.84 | J72: -1.31 | K72: 3.69 | L72: 5.38 | M72: 8.46 | N72: 9.54 | O72: 9.67 | P72: 10.47 | Q72: 14.83
A73: Open-End Funds | B73: Income (Annualized Return ) | C73: NIT Social Impact Fund | D73: A+(f) | E73: N/A | F73: 46108 | G73: 11.0961 | H73: 10.84 | I73: 10.57 | J73: 10.18 | K73: 10.53 | L73: 10.64 | M73: 10.98 | N73: 10.96 | O73: 10.84 | P73: 11.16 | Q73: 15.3
A74: Open-End Funds | B74: Income (Annualized Return ) | C74: Pak Oman Income Fund | D74: A+(f) | E74: N/A | F74: 46108 | G74: 11.5248 | H74: 7.73 | I74: 5.95 | J74: 4.42 | K74: 5.99 | L74: 5.97 | M74: 7.09 | N74: 7.37 | O74: 7.73 | P74: 7.97 | Q74: 12.37
A75: Open-End Funds | B75: Income (Annualized Return ) | C75: Pak Oman Micro Finance Fund | E75: N/A | F75: 46108 | G75: 108.6587 | H75: 14.44 | I75: 10.77 | J75: 10.73 | K75: 10.77 | L75: 10.77 | M75: 11.01 | N75: 11.11 | O75: 10.91 | P75: 11.01 | Q75: N/A
A76: Open-End Funds | B76: Income (Annualized Return ) | C76: Pakistan Income Fund | D76: AA(f) | E76: N/A | F76: 46108 | G76: 62.8879 | H76: 19.32 | I76: 7.24 | J76: 2.08 | K76: 7.22 | L76: 7.29 | M76: 35.41 | N76: 22.94 | O76: 19.32 | P76: 18.02 | Q76: 20.48
A77: Open-End Funds | B77: Income (Annualized Return ) | C77: UBL Government Securities Fund | D77: AA(f) | E77: N/A | F77: 46110 | G77: 113.9274 | H77: 9.33 | I77: -7.47 | J77: 9.89 | K77: -5.4 | L77: -6.91 | M77: 3.56 | N77: 8.61 | O77: 9.14 | P77: 11.51 | Q77: 17
A78: Open-End Funds | B78: Income (Annualized Return ) | C78: UBL Income Opportunity Fund | D78: AA-(f) | E78: N/A | F78: 46110 | G78: 116.3571 | H78: 10.59 | I78: 2.47 | J78: 12.05 | K78: -0.27 | L78: 2.73 | M78: 7.72 | N78: 10.03 | O78: 10.47 | P78: 11.37 | Q78: 16.25
A79: Open-End Funds | B79: Equity (Absolute Return ) | C79: ABL Stock Fund | E79: N/A | F79: 46108 | G79: 33.6982 | H79: 19.02 | I79: -10.67 | J79: -1 | K79: -1.99 | L79: -8.76 | M79: -13.2 | N79: -7.52 | O79: 19.02 | P79: 23.68 | Q79: 125.96
A80: Open-End Funds | B80: Equity (Absolute Return ) | C80: AKD Opportunity Fund | E80: N/A | F80: 46108 | G80: 183.4672 | H80: 10.3 | I80: -10.39 | J80: -1.12 | K80: -2.97 | L80: -9.87 | M80: -19.14 | N80: -16.39 | O80: 10.3 | P80: 24.72 | Q80: 83.11
A81: Open-End Funds | B81: Equity (Absolute Return ) | C81: AL Habib Stock Fund | E81: N/A | F81: 46107 | G81: 157.3036 | H81: 21.95 | I81: -10.74 | J81: -3.72 | K81: -3.04 | L81: -9.63 | M81: -10.98 | N81: -5.94 | O81: 22.44 | P81: 30.76 | Q81: 168.17
A82: Open-End Funds | B82: Equity (Absolute Return ) | C82: Alfalah GHP Alpha Fund | E82: N/A | F82: 46108 | G82: 101.59 | H82: 20.71 | I82: -12.2 | J82: -0.97 | K82: -2.78 | L82: -10.04 | M82: -14.31 | N82: -5.9 | O82: 20.71 | P82: 29.35 | Q82: 140.58
A83: Open-End Funds | B83: Equity (Absolute Return ) | C83: Alfalah GHP Stock Fund | E83: N/A | F83: 46108 | G83: 174.2305 | H83: 18.46 | I83: -11.87 | J83: -1 | K83: -2.79 | L83: -9.86 | M83: -14.87 | N83: -6.9 | O83: 18.46 | P83: 23.35 | Q83: 128.21
A84: Open-End Funds | B84: Equity (Absolute Return ) | C84: Alfalah Stock Fund - II | E84: N/A | F84: 46108 | G84: 68.7861 | H84: 8.02 | I84: -13.99 | J84: -1.27 | K84: -4.04 | L84: -12.47 | M84: -15.37 | N84: -8.27 | O84: 8.02 | P84: 16.14 | Q84: 126.52
A85: Open-End Funds | B85: Equity (Absolute Return ) | C85: Atlas Dividend Yield Fund | E85: N/A | F85: 46108 | G85: 86.6346 | H85: -13.37 | I85: -8.61 | J85: -0.67 | K85: -1.4 | L85: -7.55 | M85: N/A | N85: N/A | O85: N/A | P85: N/A | Q85: N/A
A86: Open-End Funds | B86: Equity (Absolute Return ) | C86: Atlas Financial Sector Fund | E86: N/A | F86: 46108 | G86: 84.9656 | H86: -15.03 | I86: -11.25 | J86: -0.57 | K86: -2.07 | L86: -9.71 | M86: N/A | N86: N/A | O86: N/A | P86: N/A | Q86: N/A
A87: Open-End Funds | B87: Equity (Absolute Return ) | C87: Atlas Stock Market Fund | E87: N/A | F87: 46108 | G87: 1873.1088 | H87: 17.11 | I87: -10.6 | J87: -0.9 | K87: -1.84 | L87: -8.46 | M87: -13.32 | N87: -8.54 | O87: 17.11 | P87: 22.77 | Q87: 124.47
A88: Open-End Funds | B88: Equity (Absolute Return ) | C88: First Capital Mutual Fund | E88: N/A | F88: 46108 | G88: 15.3891 | H88: 14.8 | I88: -9.88 | J88: -1.1 | K88: -2 | L88: -7.89 | M88: -13.37 | N88: -9.91 | O88: 14.8 | P88: 15.17 | Q88: 86.84
A89: Open-End Funds | B89: Equity (Absolute Return ) | C89: Golden Arrow Stock Fund | E89: N/A | F89: 46108 | G89: 30.9058 | H89: 5.72 | I89: -10.94 | J89: -0.87 | K89: -2.97 | L89: -10.35 | M89: -19.31 | N89: -19.97 | O89: 5.72 | P89: 17.17 | Q89: 97.32
A90: Open-End Funds | B90: Equity (Absolute Return ) | C90: HBL Energy Fund | E90: N/A | F90: 46108 | G90: 30.634 | H90: 14.47 | I90: -5.24 | J90: -2.06 | K90: -2.73 | L90: -2.9 | M90: -8.91 | N90: -8.23 | O90: 14.47 | P90: 8.96 | Q90: 92.01
A91: Open-End Funds | B91: Equity (Absolute Return ) | C91: HBL Equity Fund | E91: N/A | F91: 46106 | G91: 197.8942 | H91: 6.13 | I91: -7.03 | J91: 2.11 | K91: 0.15 | L91: -6.95 | M91: -19.49 | N91: -16.89 | O91: 6.52 | P91: 3.22 | Q91: 94.99
A92: Open-End Funds | B92: Equity (Absolute Return ) | C92: HBL Growth Fund-Class A | E92: N/A | F92: 46108 | G92: 39.5869 | H92: -6.39 | I92: -9.08 | J92: -2.03 | K92: -2.27 | L92: -4.97 | M92: -22.18 | N92: -20.78 | O92: -6.39 | P92: -13.95 | Q92: 92.17
A93: Open-End Funds | B93: Equity (Absolute Return ) | C93: HBL Growth Fund-Class B | E93: N/A | F93: 46108 | G93: 35.3284 | H93: 11.87 | I93: -11.6 | J93: -1.41 | K93: -2.7 | L93: -9.28 | M93: -18.58 | N93: -12.77 | O93: 11.87 | P93: 10.6 | Q93: 83.03
A94: Open-End Funds | B94: Equity (Absolute Return ) | C94: HBL Investment Fund-Class A | E94: N/A | F94: 46108 | G94: 14.2978 | H94: -6.02 | I94: -9.11 | J94: -2.08 | K94: -5.75 | L94: -5.07 | M94: -22.28 | N94: -20.53 | O94: -6.02 | P94: -14.15 | Q94: 94.07
A95: Open-End Funds | B95: Equity (Absolute Return ) | C95: HBL Investment Fund-Class B | E95: N/A | F95: 46108 | G95: 16.5708 | H95: 12.67 | I95: -11.35 | J95: -1.37 | K95: -2.64 | L95: -9.07 | M95: -16.55 | N95: -11.01 | O95: 12.67 | P95: 12.71 | Q95: 81.57
A96: Open-End Funds | B96: Equity (Absolute Return ) | C96: HBL Stock Fund | E96: N/A | F96: 46108 | G96: 190.8739 | H96: 11.98 | I96: -11.58 | J96: -1.05 | K96: -2.29 | L96: -9.66 | M96: -17.55 | N96: -13.77 | O96: 11.98 | P96: 10.57 | Q96: 77.31
A97: Open-End Funds | B97: Equity (Absolute Return ) | C97: JS Growth Fund | E97: N/A | F97: 46108 | G97: 469.93 | H97: 19.73 | I97: -11.72 | J97: -0.96 | K97: -2.5 | L97: -9.88 | M97: -16.38 | N97: -11.46 | O97: 19.73 | P97: 24.6 | Q97: 111.16
A98: Open-End Funds | B98: Equity (Absolute Return ) | C98: JS Large Cap Fund | E98: N/A | F98: 46108 | G98: 377.92 | H98: 17.77 | I98: -12.69 | J98: -0.96 | K98: -3.08 | L98: -10.8 | M98: -16.95 | N98: -12.09 | O98: 17.77 | P98: 23.07 | Q98: 116.09
... A113: Open-End Funds | B113: Capital Protected (Absolute Return ) | C113: Alfalah Special Savings Fund - II | E113: N/A | F113: 46108 | G113: 114.5913 | H113: 7.24 | I113: 0.64 | J113: 0.04 | K113: 0.37 | L113: 0.71 | M113: 2.29 | N113: 5.02 | O113: 7.24 | P113: 13.3 | Q113: 53.85
A114: Open-End Funds | B114: Capital Protected - Income (Annualized Return ) | C114: UBL Special Savings Plan V | E114: N/A | F114: 46110 | G114: 100.8735 | H114: 9.22 | I114: 10.22 | J114: 8.72 | K114: 9.21 | L114: 10.25 | M114: 8.94 | N114: 9.16 | O114: 9.22 | P114: 9.61 | Q114: N/A
A115: Open-End Funds | B115: Capital Protected - Income (Annualized Return ) | C115: UBL Special Savings Plan X | E115: N/A | F115: 46110 | G115: 109.1252 | H115: 9.31 | I115: 0.92 | J115: 8.91 | K115: 2.19 | L115: 1.2 | M115: 5.63 | N115: 8.95 | O115: 9.25 | P115: 11.11 | Q115: 4.98
A116: Open-End Funds | B116: Fixed Rate / Return (Annualized Return ) | C116: ABL Fixed Rate Plan XIX | E116: Average three (3) months PKRV Rates | F116: 46108 | G116: 10.7884 | H116: 10.66 | I116: 9.85 | J116: 9.49 | K116: 10.1 | L116: 9.86 | M116: 10.24 | N116: 10.76 | O116: 10.66 | P116: N/A | Q116: N/A
A117: Open-End Funds | B117: Fixed Rate / Return (Annualized Return ) | C117: ABL Fixed Rate Plan XXII | E117: N/A | F117: 46108 | G117: 10.3434 | H117: 10.99 | I117: 9.71 | J117: 13.76 | K117: 9.76 | L117: 9.57 | M117: 10.02 | N117: N/A | O117: N/A | P117: N/A | Q117: N/A
A118: Open-End Funds | B118: Fixed Rate / Return (Annualized Return ) | C118: ABL Fixed Rate Plan XXIII | E118: N/A | F118: 46108 | G118: 10.319 | H118: 10.88 | I118: 9.66 | J118: 13.8 | K118: 9.71 | L118: 9.52 | M118: 9.94 | N118: N/A | O118: N/A | P118: N/A | Q118: N/A
A119: Open-End Funds | B119: Fixed Rate / Return (Annualized Return ) | C119: ABL Fixed Rate Plan XXIV | E119: N/A | F119: 46108 | G119: 10.1182 | H119: 9.59 | I119: 9.63 | J119: 13.72 | K119: 9.68 | L119: 9.49 | M119: N/A | N119: N/A | O119: N/A | P119: N/A | Q119: N/A
...

Sheet Credit Line 
C1: 1000000
A2: Pak Oman Facility | G2: 29th December 2025 (Date of Facility Drawdown)
B3: Currently Placed | G3: KIBOR | H3: 0.1063
A4: Credit Line | B4: Amount | C4: Markup Rate | D4: Markup Payment (Annual) | G4: Spread | H4: -0.0005
B5: =1238*C1 -> 1238000000 | C5: =H5 -> 0.1058 | D5: =B5*(C5*(90/365)) -> 32296537 | G5: Facility Rate | H5: =H3+H4 -> 0.1058
A8: COI Placement | B8: Amount | C8: Rate | D8: Profit (Monthly)
B9: ='WoW Positions'!C15 -> 1300000000 | C9: 0.1005 | D9: =B9*C9*(30/365) -> 10738356
A10: Markup Payment (Net COI return) | D10: =D5-D9 -> 21558181
G11: Reset KIBOR Analysis (Facility Reset Date is 29th March 2026)
F12: =today() -> 46109 | G12: KIBOR | H12: 0.1134
B13: Reset Facility Rate (will be lock in for next 3 months) | G13: Spread | H13: -0.0005
G14: Facility Rate | H14: =H12+H13 -> 0.1129
B15: Amount | C15: Markup Rate | D15: Markup Payment - (Quartely)
B16: =B5 -> 1238000000 | C16: =H14 -> 0.1129 | D16: =B16*(C16*(90/365)) -> 34463885
B18: Increase in Markup | D18: =D16-D5 -> 2167347.9
B22: Short Term Financing Facility - Pak Oman | D22: Investments in COIs
B23: Facility Amount - (Drawdown) | C23: =B5 -> 1238000000 | D23: Certificate of Investment | E23: =B9 -> 1300000000
B24: Markup Rate | C24: =C5 -> 0.1058 | D24: Rate | E24: 0.1005
B25: Markup Amount (Finance Cost Pre Tax) | C25: =C23*C24 -> 130980400 | D25: Amount | E25: =E23*E24 -> 130650000
B26: Tax Shield Calculation | D26: Tax Rate | E26: 0.2
B27: Rate | C27: 0.39 | D27: Profit Amount (Post Tax) | E27: =E25*(1-E26) -> 104520000
B28: Tax Shield | C28: =C25*C27 -> 51082356
B29: Effective Cost of Borrowing (Post Tax)
B30: Net Cost of Borrowing (After Tax) | C30: =C25*(1-C27) -> 79898044
B31: Effective Rate - (Pre Tax) | C31: =C24 -> 0.1058
B32: Effective Rate - (Post Tax) | C32: =C30/C23 -> 0.064538
B33: Net Payable against Gross COIs Investment Profit | E33: =E25-C25 -> -330400
B34: Net Payable against Net COIs Investment Profit | E34: =E27-C25 -> -26460400
B36: Note:
B37: Assumes full tax deductibility of finance cost at 39% effective tax rate.
B40: Financial Reporting Liability
B41: =B23 -> Facility Amount - (Drawdown) | C41: =C23 -> 1238000000
B42: Markup on Loan | C42: =C41*C24*(2/365) -> 717700.82
B43: Total Liabilities | C43: =C41+C42 -> 1238717701

Sheet Analysis on MTBs Sell off
B2: Analysis on the 1 Year MTB Sell
B3: Key Assumptions
B4: Sell Yield | C4: 0.1025 | D4: Assumed
B5: Reinvestment Yield | C5: 0.115 | D5: Assumed
B6: CGT Rate | C6: 0.15
M7: Market Value (Assumed)
B8: Instrument | C8: Amount | D8: Rate | E8: Issue Date | F8: Maturity Date | G8: Today | H8: Days Held | I8: Days to Maturity | J8: Accrued Interest | K8: Current Value | L8: Total Value | M8: Market Yield | N8: Market Value | O8: Unrealized Gain/Loss
B9: MTB (1Yr) | C9: ='WoW Positions'!C9 -> 1312778062 | D9: 0.1055 | E9: 46072 | F9: =E9+364 -> 46436 | G9: =today() -> 46109 | H9: =G9-E9 -> 37 | I9: =F9-G9 -> 327 | J9: =C9*D9*H9/365 -> 14039532 | K9: =J9+C9 -> 1326817594 | L9: =C9+C9*(D9*(I9/365)) -> 1436857169 | M9: 0.1025 | N9: =C9+(C9*(M9*I9/365)) -> 1433328853 | O9: =N9-L9 -> -3528315.8
B10: MTB (1Yr) | C10: ='WoW Positions'!C10 -> 384022350 | D10: 0.107 | E10: 46086 | F10: =E10+364 -> 46450 | G10: =today() -> 46109 | H10: =G10-E10 -> 23 | I10: =F10-G10 -> 341 | J10: =C10*D10*H10/365 -> 2589257.5 | K10: =J10+C10 -> 3.8661161e+08 | L10: =C10+C10*(D10*(I10/365)) -> 4.2241091e+08 | M10: 0.1045 | N10: =C10+(C10*(M10*I10/365)) -> 4.2151398e+08 | O10: =N10-L10 -> -896928.91
O11: =SUM(O9:O10) -> -4425244.7
B13: Sell Analysis
B14: Instrument | C14: Book Value | D14: Market Value | E14: Accrued Interest | F14: Sale Proceeds | G14: Cap Gain/Loss | H14: Tax Rate | I14: Tax | J14: Net Proceeds
B15: =B9 -> MTB (1Yr) | C15: =C9 -> 1312778062 | D15: =N9 -> 1433328853 | E15: =J9 -> 14039532 | F15: =E15+D15 -> 1447368385 | G15: =D15-C15 -> 1.2055079e+08 | H15: =C6 -> 0.15 | I15: 0 | J15: =F15+I15 -> 1447368385
B16: =B10 -> MTB (1Yr) | C16: =C10 -> 384022350 | D16: =N10 -> 4.2151398e+08 | E16: =J10 -> 2589257.5 | F16: =E16+D16 -> 4.2410324e+08 | G16: =D16-C16 -> 37491629 | H16: =H15 -> 0.15 | I16: 0 | J16: =F16+I16 -> 4.2410324e+08
J17: =SUM(J15:J16) -> 1871471621
B18: Note:
B19: No tax will be applicable on the Capital Loss scenario.
B21: Reinvestment
B22: Instrument | C22: Total Net Proceeds | D22: Reinvestment Yield | E22: =I8 -> Days to Maturity | F22: Projected Accured Interest | G22: Prior Portfolio Yield | H22: Incremental Yield | I22: Incremental Income
B23: =B15 -> MTB (1Yr) | C23: =J17 -> 1871471621 | D23: =C5 -> 0.115 | E23: 365 | F23: =C23*D23*(E23/365) -> 2.1521924e+08 | G23: =SUMPRODUCT(C9:C10,D9:D10)/sum(C9:C10) -> 0.10583948 | H23: =D23-G23 -> 0.0091605178 | I23: =H23*C23 -> 17143649
B25: Net Position | C25: =O9+O10+I23 -> 12718404

Sheet Leverage
B2: Particulars | C2: Size | D2: Rate | E2: Period | F2: Interest/Return
B3: Credit Line (Additional/New) | C3: 761904762 | D3: -0.1045 | E3: 365 | F3: =C3*D3*E3/365 -> -79619048
B4: Certificate of Investment | C4: =C3*1.05 -> 8e+08 | D4: 0.1005 | E4: 365 | F4: =C4*D4*E4/365 -> 80400000
B5: Alfalah Income Multiplier Fund | C5: =C3 -> 761904762 | D5: 0.1075 | E5: 365 | F5: =C5*D5*E5/365 -> 81904762
F6: =F5+F4+F3 -> 82685714
C7: W/o leverage | D7: W leverage | E7: Differential
B8: Tax Rate | C8: 0.39 | D8: 0.32
B9: After Tax Return | C9: =F4*(1-C8) -> 49044000 | D9: =F6*(1-D8) -> 56226286
B10: Gross spread | C10: =C9/C4/(1-C8) -> 0.1005 | D10: =F6/C5 -> 0.108525
B11: Net spread | C11: =C9/(C4*365/E3) -> 0.061305 | D11: =D9/C4*365/E3 -> 0.070282857 | E11: =D11-C11 -> 0.0089778571
B13: *Net spread is calculated at effective tax rate (ETR)
B15: Profit on Monthly COIs Placement
B16: Placement Size | C16: =C4 -> 8e+08
B17: Profit Rate | C17: 0.1005 | E17: Date of Maturity | F17: 46051
B18: Tenure (Monthly Placement) | C18: =F19 -> 31 | E18: Date of Issue | F18: 46020
B19: Profit (Pre Tax) | C19: =C16*((C17*C18)/365) -> 6828493.2 | F19: =F17-F18 -> 31
B20: Tax @ 20% - (Profit of Debt) | C20: =C19*0.2 -> 1365698.6
B21: Profit (After Tax) | C21: =C19*0.8 -> 5462794.5
B22: Payment Received in Two Tranches | C22: =C21/2 -> 2731397.3
B24: Note:
B25: *Payment received in two tranches as two COIs amounting PKR 650Mn each were placed at 10.05%

Sheet Portfolio Interest Rate Sensiti
B1: Total Allocation | C1: 1000000000
B2: Current Bank Rate | C2: 0.1025
B3: PIB Rate (3 Year) | C3: 0.1024
B4: Fund Rate | C4: 0.107
B5: PIB Allocation | C5: 500000000
B6: Fund Allocation | C6: 300000000
B7: Bank Allocation | C7: 200000000
B8: 3MK | C8: 0.1036
B9: Holding Period | C9: 90
B11: Easing Scenario (bps) | C11: Policy Rate | D11: Rate Change (bps) | E11: Rate of Return | F11: PIB Discount | G11: PIB Income | H11: Fund Income | I11: Bank Income | J11: Total Portfolio Yield | K11: Gain over Savings | L11: Benchmark | M11: Alpha
B12: 0 | C12: 0.105 | D12: 0 | E12: =$C$2+D12 -> 0.1025 | F12: 0.102 | G12: =$C$5*F12*$C$9/365 -> 12575342 | H12: =$C$6*($C$4-D12)*$C$9/365 -> 7915068.5 | I12: =$C$7*E12*$C$9/365 -> 5054794.5 | J12: =SUM(G12:I12)/$C$1*365/90 -> 0.1036 | K12: =J12-E12 -> 0.0011 | L12: =$C$8-1%+D12 -> 0.0936 | M12: =J12-L12 -> 0.01
B13: 25 | C13: =$C$12+D13/10000 -> 0.10499975 | D13: -0.0025 | E13: =$C$2+D13 -> 0.1 | F13: =$F$12+($F$12*(-D13*0.75)) -> 0.10219125 | G13: =$C$5*F13*$C$9/365 -> 12598921 | H13: =$C$6*($C$4-D13)*$C$9/365 -> 8100000 | I13: =$C$7*E13*$C$9/365 -> 4931506.8 | J13: =SUM(G13:I13)/$C$1*365/90 -> 0.10394562 | K13: =J13-E13 -> 0.003945625 | L13: =$C$8-1%+D13 -> 0.0911 | M13: =J13-L13 -> 0.012845625
B14: 50 | C14: =$C$12+D14/10000 -> 0.1049995 | D14: -0.005 | E14: =$C$2+D14 -> 0.0975 | F14: =$F$12+($F$12*(-D14*0.75)) -> 0.1023825 | G14: =$C$5*F14*$C$9/365 -> 12622500 | H14: =$C$6*($C$4-D14)*$C$9/365 -> 8284931.5 | I14: =$C$7*E14*$C$9/365 -> 4808219.2 | J14: =SUM(G14:I14)/$C$1*365/90 -> 0.10429125 | K14: =J14-E14 -> 0.00679125 | L14: =$C$8-1%+D14 -> 0.0886 | M14: =J14-L14 -> 0.01569125
B15: 75 | C15: =$C$12+D15/10000 -> 0.10499925 | D15: -0.0075 | E15: =$C$2+D15 -> 0.095 | F15: =$F$12+($F$12*(-D15*0.75)) -> 0.10257375 | G15: =$C$5*F15*$C$9/365 -> 12646079 | H15: =$C$6*($C$4-D15)*$C$9/365 -> 8469863 | I15: =$C$7*E15*$C$9/365 -> 4684931.5 | J15: =SUM(G15:I15)/$C$1*365/90 -> 0.10463688 | K15: =J15-E15 -> 0.009636875 | L15: =$C$8-1%+D15 -> 0.0861 | M15: =J15-L15 -> 0.018536875
B18: Placements | C18: Composition | D18: {=TRANSPOSE(B12:B15)} -> 0 | E18: 25 | F18: 50 | G18: 75
B19: Cash | C19: 0.46 | D19: {=TRANSPOSE(E12:E15)} -> 0.1025 | E19: 0.1 | F19: 0.0975 | G19: 0.095
B20: Ijarah/Sukuk | C20: 0.007 | D20: 0.104 | E20: =D20+D13 -> 0.1015 | F20: =D20+D14 -> 0.099 | G20: =D20+D15 -> 0.0965
B21: PIBs | C21: 0.077 | D21: 0.11 | E21: =D21-(0.5*D13) -> 0.11125 | F21: =E21-(0.5*D14) -> 0.11375 | G21: =F21-(0.5*D15) -> 0.1175
B22: TFC | C22: 0.014 | D22: 0.11 | E22: =D22 -> 0.11 | F22: =E22 -> 0.11 | G22: =F22 -> 0.11
B23: CPs | C23: 0.133 | D23: 0.115 | E23: =D23 -> 0.115 | F23: =E23 -> 0.115 | G23: =F23 -> 0.115
B24: MTS | C24: 0.26 | D24: 0.125 | E24: =D24-D13 -> 0.1275 | F24: =D24-D14 -> 0.13 | G24: =D24-D15 -> 0.1325
B25: Others | C25: 0.045 | D25: =D19+0.5% -> 0.1075 | E25: =E19+0.5% -> 0.105 | F25: =F19+0.5% -> 0.1025 | G25: =G19+0.5% -> 0.1
D26: =SUMPRODUCT($C$19:$C$25,D19:D25) -> 0.1105205 | E26: =SUMPRODUCT($C$19:$C$25,E19:E25) -> 0.10998675 | F26: =SUMPRODUCT($C$19:$C$25,F19:F25) -> 0.10954925 | G26: =SUMPRODUCT($C$19:$C$25,G19:G25) -> 0.109208
C28: PIB | D28: 3
C29: FV | D29: 500000000 | E29: =TODAY() -> 46109
C30: Cost of placement | D30: =-PV(10.24%,3,0,D29) -> 3.7320924e+08 | E30: =E29+D31 -> 46199
C31: Holding Period | D31: 90
C32: Duration | D32: =DURATION(E29,E30,10.24%,10.24%,1) -> 0.24444444
C34: Interest per day | D34: =(D29-D30)/(365*3) -> 115790.65
C35: Accrued Interest | D35: =D34*D31 -> 10421158
C37: Rate Cut | D37: 0.0025 | E37: 0.005 | F37: =E37+D37 -> 0.0075
D38: =D37*($D$28-$D$32) -> 0.0068888889 | E38: =E37*($D$28-$D$32) -> 0.013777778 | F38: =F37*($D$28-$D$32) -> 0.020666667
D39: =D38*$D$29 -> 3444444.4 | E39: =E38*$D$29 -> 6888888.9 | F39: =F38*$D$29 -> 10333333
D40: =$D$35+D39 -> 13865603 | E40: =$D$35+E39 -> 17310047 | F40: =$D$35+F39 -> 20754491
D41: =RATE(1,0,-$D$30+D39,$D$29) -> 0.35221093 | E41: =RATE(1,0,-$D$30+E39,$D$29) -> 0.36492552 | F41: =RATE(1,0,-$D$30+F39,$D$29) -> 0.37788149
C42: Rate | D42: =(1+D41)^(1/3)-1 -> 0.10581246 | E42: =(1+E41)^(1/3)-1 -> 0.10926757 | F42: =(1+F41)^(1/3)-1 -> 0.11276628
